<?xml version="1.0" encoding="UTF-8" standalone="no" ?>
<Application>

  <Header>
    <Version val="13030.00"/>
    <WithIsn val="Y"/>
    <_InternalTask val="N"/>
    <IsRoot val="N"/>
    <InIndex val="N"/>
    <UniqueISNConvState val="12"/>
  </Header>

  <ProgramsRepository>
    <Programs>
      <Task MainProgram="N">
        <Header Description="BDC120FL=CheckFL_LimitAllowed" ISN_2="1" LastIsn="1" id="638">
          <Public val="BDC120_FL"/>
          <ExecutionRight comp="-1"/>
          <Resident val="N"/>
          <SQL val="N"/>
          <ReturnValue>
            <ReturnValueAttr/>
            <TSK_PARAMS val="7"/>
            <ParametersAttributes>
              <Attr MgAttr="N"/>
              <Attr MgAttr="N"/>
              <Attr MgAttr="U"/>
              <Attr MgAttr="N"/>
              <Attr MgAttr="U"/>
              <Attr MgAttr="U"/>
              <Attr MgAttr="U"/>
            </ParametersAttributes>
          </ReturnValue>
          <SqlWhereExist val="N"/>
          <TaskType val="B"/>
          <External val="N"/>
          <Offline val="N"/>
          <FormType val="N"/>
          <DotNetObjectExists val="N"/>
          <LastModified _date="734982" _time="58568" date="24/04/2013" time="16:16:08"/>
        </Header>
        <ItemIsn val="34"/>
        <Resource>
          <DB id="1">
            <DataObject comp="-1" obj="6"/>
            <Access val="R"/>
            <Share val="W"/>
            <Open val="N"/>
            <Cache val="N"/>
            <IdentifyRowModifications val="84"/>
          </DB>
          <DB id="2">
            <DataObject comp="-1" obj="53"/>
            <Access val="R"/>
            <Share val="W"/>
            <Open val="N"/>
            <Cache val="N"/>
            <IdentifyRowModifications val="84"/>
          </DB>
          <DB id="3">
            <DataObject comp="-1" obj="342"/>
            <Access val="R"/>
            <Share val="W"/>
            <Open val="N"/>
            <Cache val="N"/>
            <IdentifyRowModifications val="84"/>
          </DB>
          <DB id="4">
            <DataObject comp="-1" obj="182"/>
            <Access val="R"/>
            <Share val="W"/>
            <Open val="N"/>
            <Cache val="N"/>
            <IdentifyRowModifications val="84"/>
          </DB>
          <DB id="5">
            <DataObject comp="-1" obj="206"/>
            <Access val="R"/>
            <Share val="W"/>
            <Open val="N"/>
            <Cache val="N"/>
            <IdentifyRowModifications val="84"/>
          </DB>
          <DB id="6">
            <DataObject comp="-1" obj="270"/>
            <Access val="R"/>
            <Share val="W"/>
            <Open val="N"/>
            <Cache val="N"/>
            <IdentifyRowModifications val="84"/>
          </DB>
          <Columns>
            <Column id="1" name="p.DEBC_NO">
              <PropertyList model="FIELD">
                <Model attr_obj="FIELD_NUMERIC" comp="-1" id="1" obj="63"/>
                <CharSet id="172" val="1"/>
                <StoredAs id="173" val="1"/>
                <Definition id="175" val="2"/>
              </PropertyList>
            </Column>
            <Column id="2" name="p.RequestedLimitAmount">
              <PropertyList model="FIELD">
                <Model attr_obj="FIELD_NUMERIC" comp="-1" id="1" obj="116"/>
                <CharSet id="172" val="1"/>
                <StoredAs id="173" val="6"/>
                <Definition id="175" val="2"/>
              </PropertyList>
            </Column>
            <Column id="3" name="p.RequestedLimitCurrency">
              <PropertyList model="FIELD">
                <Model attr_obj="FIELD_UNICODE" comp="-1" id="1" obj="50"/>
                <StoredAs id="173" val="31"/>
                <Definition id="175" val="2"/>
              </PropertyList>
            </Column>
            <Column id="4" name="po.DecisionLimitAmount">
              <PropertyList model="FIELD">
                <Model attr_obj="FIELD_NUMERIC" comp="-1" id="1" obj="116"/>
                <CharSet id="172" val="1"/>
                <StoredAs id="173" val="6"/>
                <Definition id="175" val="2"/>
              </PropertyList>
            </Column>
            <Column id="5" name="po.DecisionLimitCurrency">
              <PropertyList model="FIELD">
                <Model attr_obj="FIELD_UNICODE" comp="-1" id="1" obj="50"/>
                <StoredAs id="173" val="31"/>
                <Definition id="175" val="2"/>
              </PropertyList>
            </Column>
            <Column id="6" name="po.TextCode">
              <PropertyList model="FIELD">
                <Model attr_obj="FIELD_UNICODE" comp="-1" id="1" obj="26"/>
                <StoredAs id="173" val="31"/>
                <Definition id="175" val="2"/>
              </PropertyList>
            </Column>
            <Column id="7" name="po.CLTC_DESCSHORT">
              <PropertyList model="FIELD">
                <Model attr_obj="FIELD_UNICODE" comp="-1" id="1" obj="130"/>
                <StoredAs id="173"/>
                <DbColumnName id="178"/>
                <Type id="179"/>
                <UserType id="180"/>
              </PropertyList>
            </Column>
            <Column id="8" name="v.LimitNotPossible">
              <PropertyList model="FIELD">
                <Model attr_obj="FIELD_LOGICAL" id="1"/>
                <GuiDisplay id="158">
                  <PropertyList model="CTRL_GUI0_EDIT">
                    <Font id="50" val="111"/>
                    <Color id="51" val="4"/>
                    <V11Style id="539" val="4"/>
                    <V11Color id="695" val="111"/>
                  </PropertyList>
                </GuiDisplay>
                <GuiDisplayTable id="159">
                  <PropertyList model="CTRL_GUI0_EDIT">
                    <Font id="50" val="111"/>
                    <Color id="51" val="4"/>
                    <V11Color id="695" val="111"/>
                  </PropertyList>
                </GuiDisplayTable>
                <GuiOutput id="160">
                  <PropertyList model="CTRL_GUI1_EDIT">
                    <Font id="50" val="111"/>
                    <Color id="51" val="111"/>
                  </PropertyList>
                </GuiOutput>
                <GuiOutputTable id="161">
                  <PropertyList model="CTRL_GUI1_EDIT">
                    <Font id="50" val="111"/>
                    <Color id="51" val="111"/>
                  </PropertyList>
                </GuiOutputTable>
                <NullValue id="167"/>
                <CharSet id="172" val="1"/>
                <StoredAs id="173" val="1"/>
                <Definition id="175" val="2"/>
              </PropertyList>
            </Column>
            <Column id="9" name="v.CalcAmount_DEBC_FL_Limit">
              <PropertyList model="FIELD">
                <Model attr_obj="FIELD_NUMERIC" comp="-1" id="1" obj="116"/>
                <CharSet id="172" val="1"/>
                <StoredAs id="173" val="6"/>
                <Definition id="175" val="2"/>
              </PropertyList>
            </Column>
            <Column id="10" name="v.CalcAmount_Requested_Limit">
              <PropertyList model="FIELD">
                <Model attr_obj="FIELD_NUMERIC" comp="-1" id="1" obj="116"/>
                <CharSet id="172" val="1"/>
                <StoredAs id="173" val="6"/>
                <Definition id="175" val="2"/>
              </PropertyList>
            </Column>
          </Columns>
        </Resource>
        <Information>
          <Key>
            <Mode val="N"/>
          </Key>
          <DB comp="-1"/>
          <Sort>
            <CLS val="A"/>
          </Sort>
          <ForceRecordDelete DEL="N"/>
          <EndTaskCondition val="Y"/>
          <EvaluateEndCondition val="A"/>
          <InitialMode val="M"/>
          <Locate Direction="A"/>
          <Range Direction="A"/>
          <VarRange/>
          <TaskProperties>
            <SelectionTable val="N"/>
            <ConfirmUpdate CNFU="N"/>
            <ConfirmCancel val="N"/>
            <ErrorStrategy val="A"/>
            <LockingStrategy val="I"/>
            <CacheStrategy val="N"/>
            <ForceRecordSuffix val="N"/>
            <TransactionMode val="P"/>
            <TransactionBegin val="T"/>
            <PreloadView val="N"/>
            <AllowEmptyDataview val="N"/>
            <KeepCreatedContext val="N"/>
          </TaskProperties>
          <SIDE_WIN>
            <AllowOptions val="N"/>
            <AllowQuery val="Y"/>
            <AllowModify val="Y"/>
            <AllowCreate val="Y"/>
            <AllowDelete val="Y"/>
            <AllowLocate val="Y"/>
            <AllowRange val="Y"/>
            <AllowIndexChange val="Y"/>
            <AllowSorting val="Y"/>
            <AllowIOFiles val="Y"/>
            <RecordCycle val="Y"/>
            <AllowEvents val="Y"/>
            <AllowIndexOptimization val="Y"/>
            <AllowLocationInQuery val="Y"/>
            <AllowPrintingData val="N"/>
          </SIDE_WIN>
          <WIN>
            <OpenTaskWindow val="N"/>
            <CloseTaskWindow val="N"/>
            <ForegroundWindow val="N"/>
            <FlipFld val="N"/>
            <RefreshTaskWindow ReturnValue="N"/>
          </WIN>
          <BOX>
            <Direction val="V"/>
          </BOX>
        </Information>
        <TaskLogic>
          <LogicUnit id="2" propagate="78">
            <Level val="R"/>
            <Type val="M"/>
            <Scope val="S"/>
            <EngineDirective val="S"/>
            <ShowMessage val="Y"/>
            <Condition val="89"/>
            <Event>
              <EventType val="S"/>
              <PublicObject comp="-1"/>
            </Event>
            <Expanded val="1"/>
            <LogicLines>
              <LogicLine>
                <DATAVIEW_SRC FlowIsn="2" Type="M">
                  <Condition val="N"/>
                  <Modifier val="B"/>
                  <Direction val="C"/>
                </DATAVIEW_SRC>
              </LogicLine>
              <LogicLine>
                <Select FieldID="1" FlowIsn="3" id="1">
                  <Column val="1"/>
                  <Type val="V"/>
                  <IsParameter val="Y"/>
                  <INT_RCMP_INFO>
                    <v>11</v>
                  </INT_RCMP_INFO>
                  <DIFF_UPDATE val="T"/>
                  <Condition val="Y"/>
                  <Modifier val="S"/>
                  <Direction val="C"/>
                </Select>
              </LogicLine>
              <LogicLine>
                <Select FieldID="2" FlowIsn="4" id="2">
                  <Column val="2"/>
                  <Type val="V"/>
                  <IsParameter val="Y"/>
                  <DIFF_UPDATE val="T"/>
                  <Condition val="Y"/>
                  <Modifier val="S"/>
                  <Direction val="C"/>
                </Select>
              </LogicLine>
              <LogicLine>
                <Select FieldID="3" FlowIsn="5" id="3">
                  <Column val="3"/>
                  <Type val="V"/>
                  <IsParameter val="Y"/>
                  <DIFF_UPDATE val="T"/>
                  <Condition val="Y"/>
                  <Modifier val="S"/>
                  <Direction val="C"/>
                </Select>
              </LogicLine>
              <LogicLine>
                <Select FieldID="4" FlowIsn="6" id="4">
                  <Column val="4"/>
                  <Type val="V"/>
                  <IsParameter val="Y"/>
                  <DIFF_UPDATE val="T"/>
                  <Condition val="Y"/>
                  <Modifier val="S"/>
                  <Direction val="C"/>
                </Select>
              </LogicLine>
              <LogicLine>
                <Select FieldID="5" FlowIsn="7" id="5">
                  <Column val="5"/>
                  <Type val="V"/>
                  <IsParameter val="Y"/>
                  <DIFF_UPDATE val="T"/>
                  <Condition val="Y"/>
                  <Modifier val="S"/>
                  <Direction val="C"/>
                </Select>
              </LogicLine>
              <LogicLine>
                <Select FieldID="6" FlowIsn="8" id="6">
                  <Column val="6"/>
                  <Type val="V"/>
                  <IsParameter val="Y"/>
                  <INT_RCMP_INFO>
                    <v>26</v>
                  </INT_RCMP_INFO>
                  <DIFF_UPDATE val="T"/>
                  <Condition val="Y"/>
                  <Modifier val="S"/>
                  <Direction val="C"/>
                </Select>
              </LogicLine>
              <LogicLine>
                <Select FieldID="7" FlowIsn="9" id="7">
                  <Column val="7"/>
                  <Type val="V"/>
                  <IsParameter val="Y"/>
                  <DIFF_UPDATE val="T"/>
                  <Condition val="Y"/>
                  <Modifier val="S"/>
                  <Direction val="C"/>
                </Select>
              </LogicLine>
              <LogicLine>
                <Remark FlowIsn="10">
                  <Type val="0"/>
                  <Text val=" "/>
                </Remark>
              </LogicLine>
              <LogicLine>
                <LNK Direction="A" EVL_CND="R" FlowIsn="11" Key="1" Mode="R" SortType="18" VIEW="8" VIEWS="6">
                  <DB comp="-1" obj="182"/>
                  <Expanded val="1"/>
                  <Condition val="Y"/>
                </LNK>
              </LogicLine>
              <LogicLine>
                <Select FieldID="8" FlowIsn="12" id="8">
                  <Column val="1"/>
                  <Type val="R"/>
                  <IsParameter val="N"/>
                  <Locate MAX="2" MIN="2"/>
                  <DIFF_UPDATE val="T"/>
                  <Condition val="Y"/>
                  <Modifier val="S"/>
                  <Direction val="C"/>
                </Select>
              </LogicLine>
              <LogicLine>
                <Select FieldID="9" FlowIsn="13" id="9">
                  <Column val="2"/>
                  <Type val="R"/>
                  <IsParameter val="N"/>
                  <INT_RCMP_INFO>
                    <v>32</v>
                  </INT_RCMP_INFO>
                  <DIFF_UPDATE val="T"/>
                  <Condition val="Y"/>
                  <Modifier val="S"/>
                  <Direction val="C"/>
                </Select>
              </LogicLine>
              <LogicLine>
                <Select FieldID="10" FlowIsn="14" id="10">
                  <Column val="4"/>
                  <Type val="R"/>
                  <IsParameter val="N"/>
                  <INT_RCMP_INFO>
                    <v>20</v>
                    <v>46</v>
                  </INT_RCMP_INFO>
                  <DIFF_UPDATE val="T"/>
                  <Condition val="Y"/>
                  <Modifier val="S"/>
                  <Direction val="C"/>
                </Select>
              </LogicLine>
              <LogicLine>
                <Select FieldID="11" FlowIsn="15" id="11">
                  <Column val="5"/>
                  <Type val="R"/>
                  <IsParameter val="N"/>
                  <INT_RCMP_INFO>
                    <v>20</v>
                  </INT_RCMP_INFO>
                  <DIFF_UPDATE val="T"/>
                  <Condition val="Y"/>
                  <Modifier val="S"/>
                  <Direction val="C"/>
                </Select>
              </LogicLine>
              <LogicLine>
                <Select FieldID="12" FlowIsn="16" id="12">
                  <Column val="38"/>
                  <Type val="R"/>
                  <IsParameter val="N"/>
                  <DIFF_UPDATE val="T"/>
                  <Condition val="Y"/>
                  <Modifier val="S"/>
                  <Direction val="C"/>
                </Select>
              </LogicLine>
              <LogicLine>
                <Select FieldID="13" FlowIsn="17" id="13">
                  <Column val="39"/>
                  <Type val="R"/>
                  <IsParameter val="N"/>
                  <DIFF_UPDATE val="T"/>
                  <Condition val="Y"/>
                  <Modifier val="S"/>
                  <Direction val="C"/>
                </Select>
              </LogicLine>
              <LogicLine>
                <END_LINK FlowIsn="18"/>
              </LogicLine>
              <LogicLine>
                <Remark FlowIsn="19">
                  <Type val="0"/>
                  <Text val=" "/>
                </Remark>
              </LogicLine>
              <LogicLine>
                <LNK Direction="A" EVL_CND="R" FlowIsn="20" Key="1" Mode="R" SortType="24" VIEW="14" VIEWS="3">
                  <DB comp="-1" obj="53"/>
                  <Expanded val="1"/>
                  <Condition val="Y"/>
                </LNK>
              </LogicLine>
              <LogicLine>
                <Select FieldID="14" FlowIsn="21" id="14">
                  <Column val="1"/>
                  <Type val="R"/>
                  <IsParameter val="N"/>
                  <Locate MAX="6" MIN="6"/>
                  <DIFF_UPDATE val="T"/>
                  <Condition val="Y"/>
                  <Modifier val="S"/>
                  <Direction val="C"/>
                </Select>
              </LogicLine>
              <LogicLine>
                <Select FieldID="15" FlowIsn="22" id="15">
                  <Column val="2"/>
                  <Type val="R"/>
                  <IsParameter val="N"/>
                  <Locate MAX="7" MIN="7"/>
                  <DIFF_UPDATE val="T"/>
                  <Condition val="Y"/>
                  <Modifier val="S"/>
                  <Direction val="C"/>
                </Select>
              </LogicLine>
              <LogicLine>
                <Select FieldID="16" FlowIsn="23" id="16">
                  <Column val="14"/>
                  <Type val="R"/>
                  <IsParameter val="N"/>
                  <DIFF_UPDATE val="T"/>
                  <Condition val="Y"/>
                  <Modifier val="S"/>
                  <Direction val="C"/>
                </Select>
              </LogicLine>
              <LogicLine>
                <END_LINK FlowIsn="24"/>
              </LogicLine>
              <LogicLine>
                <Remark FlowIsn="25">
                  <Type val="0"/>
                  <Text val=" "/>
                </Remark>
              </LogicLine>
              <LogicLine>
                <LNK Direction="A" EVL_CND="R" FlowIsn="26" Key="1" Mode="R" SortType="30" VIEW="17" VIEWS="3">
                  <DB comp="-1" obj="342"/>
                  <Expanded val="1"/>
                  <Condition val="Y"/>
                </LNK>
              </LogicLine>
              <LogicLine>
                <Select FieldID="17" FlowIsn="27" id="17">
                  <Column val="1"/>
                  <Type val="R"/>
                  <IsParameter val="N"/>
                  <Locate MAX="22" MIN="22"/>
                  <DIFF_UPDATE val="T"/>
                  <Condition val="Y"/>
                  <Modifier val="S"/>
                  <Direction val="C"/>
                </Select>
              </LogicLine>
              <LogicLine>
                <Select FieldID="18" FlowIsn="28" id="18">
                  <Column val="2"/>
                  <Type val="R"/>
                  <IsParameter val="N"/>
                  <Locate MAX="23" MIN="23"/>
                  <DIFF_UPDATE val="T"/>
                  <Condition val="Y"/>
                  <Modifier val="S"/>
                  <Direction val="C"/>
                </Select>
              </LogicLine>
              <LogicLine>
                <Select FieldID="19" FlowIsn="29" id="19">
                  <Column val="3"/>
                  <Type val="R"/>
                  <IsParameter val="N"/>
                  <DIFF_UPDATE val="T"/>
                  <Condition val="Y"/>
                  <Modifier val="S"/>
                  <Direction val="C"/>
                </Select>
              </LogicLine>
              <LogicLine>
                <END_LINK FlowIsn="30"/>
              </LogicLine>
              <LogicLine>
                <Remark FlowIsn="31">
                  <Type val="0"/>
                  <Text val=" "/>
                </Remark>
              </LogicLine>
              <LogicLine>
                <LNK Direction="A" EVL_CND="R" FlowIsn="32" Key="1" Mode="R" SortType="38" VIEW="20" VIEWS="5">
                  <DB comp="-1" obj="206"/>
                  <Expanded val="1"/>
                  <Condition val="Y"/>
                </LNK>
              </LogicLine>
              <LogicLine>
                <Select FieldID="20" FlowIsn="33" id="20">
                  <Column val="1"/>
                  <Type val="R"/>
                  <IsParameter val="N"/>
                  <Locate MAX="5" MIN="5"/>
                  <DIFF_UPDATE val="T"/>
                  <Condition val="Y"/>
                  <Modifier val="S"/>
                  <Direction val="C"/>
                </Select>
              </LogicLine>
              <LogicLine>
                <Select FieldID="21" FlowIsn="34" id="21">
                  <Column val="7"/>
                  <Type val="R"/>
                  <IsParameter val="N"/>
                  <DIFF_UPDATE val="T"/>
                  <Condition val="Y"/>
                  <Modifier val="S"/>
                  <Direction val="C"/>
                </Select>
              </LogicLine>
              <LogicLine>
                <Select FieldID="22" FlowIsn="35" id="22">
                  <Column val="22"/>
                  <Type val="R"/>
                  <IsParameter val="N"/>
                  <DIFF_UPDATE val="T"/>
                  <Condition val="Y"/>
                  <Modifier val="S"/>
                  <Direction val="C"/>
                </Select>
              </LogicLine>
              <LogicLine>
                <Select FieldID="23" FlowIsn="36" id="23">
                  <Column val="44"/>
                  <Type val="R"/>
                  <IsParameter val="N"/>
                  <DIFF_UPDATE val="T"/>
                  <Condition val="Y"/>
                  <Modifier val="S"/>
                  <Direction val="C"/>
                </Select>
              </LogicLine>
              <LogicLine>
                <Select FieldID="24" FlowIsn="37" id="24">
                  <Column val="45"/>
                  <Type val="R"/>
                  <IsParameter val="N"/>
                  <DIFF_UPDATE val="T"/>
                  <Condition val="Y"/>
                  <Modifier val="S"/>
                  <Direction val="C"/>
                </Select>
              </LogicLine>
              <LogicLine>
                <END_LINK FlowIsn="38"/>
              </LogicLine>
              <LogicLine>
                <Remark FlowIsn="39">
                  <Type val="0"/>
                  <Text val=" "/>
                </Remark>
              </LogicLine>
              <LogicLine>
                <LNK Direction="A" EVL_CND="R" FlowIsn="40" Key="1" Mode="R" SortType="44" VIEW="25" VIEWS="3">
                  <DB comp="-1" obj="270"/>
                  <Expanded val="1"/>
                  <Condition val="Y"/>
                </LNK>
              </LogicLine>
              <LogicLine>
                <Select FieldID="25" FlowIsn="41" id="25">
                  <Column val="1"/>
                  <Type val="R"/>
                  <IsParameter val="N"/>
                  <DIFF_UPDATE val="T"/>
                  <Condition val="Y"/>
                  <Modifier val="S"/>
                  <Direction val="C"/>
                </Select>
              </LogicLine>
              <LogicLine>
                <Select FieldID="26" FlowIsn="42" id="26">
                  <Column val="102"/>
                  <Type val="R"/>
                  <IsParameter val="N"/>
                  <DIFF_UPDATE val="T"/>
                  <Condition val="Y"/>
                  <Modifier val="S"/>
                  <Direction val="C"/>
                </Select>
              </LogicLine>
              <LogicLine>
                <Select FieldID="27" FlowIsn="43" id="27">
                  <Column val="105"/>
                  <Type val="R"/>
                  <IsParameter val="N"/>
                  <DIFF_UPDATE val="T"/>
                  <Condition val="Y"/>
                  <Modifier val="S"/>
                  <Direction val="C"/>
                </Select>
              </LogicLine>
              <LogicLine>
                <END_LINK FlowIsn="44"/>
              </LogicLine>
              <LogicLine>
                <Remark FlowIsn="45">
                  <Type val="0"/>
                  <Text val=" "/>
                </Remark>
              </LogicLine>
              <LogicLine>
                <LNK Direction="A" EVL_CND="R" FlowIsn="46" Key="1" Mode="R" SortType="51" VIEW="28" VIEWS="4">
                  <DB comp="-1" obj="6"/>
                  <Expanded val="1"/>
                  <Condition val="Y"/>
                </LNK>
              </LogicLine>
              <LogicLine>
                <Select FieldID="28" FlowIsn="47" id="28">
                  <Column val="1"/>
                  <Type val="R"/>
                  <IsParameter val="N"/>
                  <Locate MAX="6" MIN="6"/>
                  <DIFF_UPDATE val="T"/>
                  <Condition val="Y"/>
                  <Modifier val="S"/>
                  <Direction val="C"/>
                </Select>
              </LogicLine>
              <LogicLine>
                <Select FieldID="29" FlowIsn="48" id="29">
                  <Column val="6"/>
                  <Type val="R"/>
                  <IsParameter val="N"/>
                  <DIFF_UPDATE val="T"/>
                  <Condition val="Y"/>
                  <Modifier val="S"/>
                  <Direction val="C"/>
                </Select>
              </LogicLine>
              <LogicLine>
                <Select FieldID="30" FlowIsn="49" id="30">
                  <Column val="36"/>
                  <Type val="R"/>
                  <IsParameter val="N"/>
                  <DIFF_UPDATE val="T"/>
                  <Condition val="Y"/>
                  <Modifier val="S"/>
                  <Direction val="C"/>
                </Select>
              </LogicLine>
              <LogicLine>
                <Select FieldID="31" FlowIsn="50" id="31">
                  <Column val="37"/>
                  <Type val="R"/>
                  <IsParameter val="N"/>
                  <DIFF_UPDATE val="T"/>
                  <Condition val="Y"/>
                  <Modifier val="S"/>
                  <Direction val="C"/>
                </Select>
              </LogicLine>
              <LogicLine>
                <END_LINK FlowIsn="51"/>
              </LogicLine>
              <LogicLine>
                <Remark FlowIsn="52">
                  <Type val="0"/>
                  <Text val=" "/>
                </Remark>
              </LogicLine>
              <LogicLine>
                <Select FieldID="32" FlowIsn="53" id="32">
                  <Column val="8"/>
                  <Type val="V"/>
                  <IsParameter val="N"/>
                  <DIFF_UPDATE val="T"/>
                  <Condition val="Y"/>
                  <Modifier val="S"/>
                  <Direction val="C"/>
                </Select>
              </LogicLine>
              <LogicLine>
                <Select FieldID="33" FlowIsn="54" id="33">
                  <Column val="9"/>
                  <Type val="V"/>
                  <IsParameter val="N"/>
                  <DIFF_UPDATE val="T"/>
                  <Condition val="Y"/>
                  <Modifier val="S"/>
                  <Direction val="C"/>
                </Select>
              </LogicLine>
              <LogicLine>
                <Select FieldID="34" FlowIsn="55" id="34">
                  <Column val="10"/>
                  <Type val="V"/>
                  <IsParameter val="N"/>
                  <DIFF_UPDATE val="T"/>
                  <Condition val="Y"/>
                  <Modifier val="S"/>
                  <Direction val="C"/>
                </Select>
              </LogicLine>
            </LogicLines>
          </LogicUnit>
          <LogicUnit id="3" propagate="78">
            <Level val="T"/>
            <Type val="P"/>
            <Scope val="S"/>
            <EngineDirective val="S"/>
            <ShowMessage val="Y"/>
            <Condition val="89"/>
            <Event>
              <EventType val="S"/>
              <PublicObject comp="-1"/>
            </Event>
            <Expanded val="1"/>
            <LogicLines>
              <LogicLine>
                <BLOCK EndBlock="69" EndBlockSegment="69" FlowIsn="56" Type="I">
                  <Condition val="N"/>
                  <Modifier val="B"/>
                  <Direction val="C"/>
                </BLOCK>
              </LogicLine>
              <LogicLine>
                <Remark FlowIsn="57">
                  <Type val="2"/>
                  <Text val="Author: Juergen Paarmann"/>
                </Remark>
              </LogicLine>
              <LogicLine>
                <Remark FlowIsn="58">
                  <Type val="2"/>
                  <Text val="Created: 13-11-2003"/>
                </Remark>
              </LogicLine>
              <LogicLine>
                <Remark FlowIsn="59">
                  <Type val="2"/>
                  <Text val="program checks, if a requested finance limit is allowed"/>
                </Remark>
              </LogicLine>
              <LogicLine>
                <Remark FlowIsn="60">
                  <Type val="2"/>
                  <Text val=" "/>
                </Remark>
              </LogicLine>
              <LogicLine>
                <Remark FlowIsn="61">
                  <Type val="2"/>
                  <Text val="24.04.2013 JH SCR18105 Removed external flag"/>
                </Remark>
              </LogicLine>
              <LogicLine>
                <Remark FlowIsn="62">
                  <Type val="2"/>
                  <Text val="10.05.2011 GB SCR16419 Removed test 3, 4 , 5"/>
                </Remark>
              </LogicLine>
              <LogicLine>
                <Remark FlowIsn="63">
                  <Type val="2"/>
                  <Text val="18.03.2011 JOH SCR16306 Replaced GNRL_CURRENCY by ADMN_CURRENCY and"/>
                </Remark>
              </LogicLine>
              <LogicLine>
                <Remark FlowIsn="64">
                  <Type val="2"/>
                  <Text val="GB002 by GB902"/>
                </Remark>
              </LogicLine>
              <LogicLine>
                <Remark FlowIsn="65">
                  <Type val="2"/>
                  <Text val="28.05.2010 GB SCR15541 Replaced table CLTC by table LTCL"/>
                </Remark>
              </LogicLine>
              <LogicLine>
                <Remark FlowIsn="66">
                  <Type val="2"/>
                  <Text val="07.01.2009 GB SCR14276 Added Test5"/>
                </Remark>
              </LogicLine>
              <LogicLine>
                <Remark FlowIsn="67">
                  <Type val="2"/>
                  <Text val="10.04.2007 AK SCR12433  added po.CLTC_DESCSHORT"/>
                </Remark>
              </LogicLine>
              <LogicLine>
                <Remark FlowIsn="68">
                  <Type val="2"/>
                  <Text val="14.11.2003 JP SCR 4773 modified copy from BDC120"/>
                </Remark>
              </LogicLine>
              <LogicLine>
                <END_BLK FlowIsn="69"/>
              </LogicLine>
              <LogicLine>
                <Remark FlowIsn="70">
                  <Type val="2"/>
                  <Text val=" "/>
                </Remark>
              </LogicLine>
              <LogicLine>
                <Remark FlowIsn="71">
                  <Type val="2"/>
                  <Text val="initialise decision values"/>
                </Remark>
              </LogicLine>
              <LogicLine>
                <Update FlowIsn="72">
                  <FieldID val="4"/>
                  <WithValue val="1"/>
                  <Incremental val="N"/>
                  <ForcedUpdate val="Y"/>
                  <Condition val="Y"/>
                  <Modifier val="B"/>
                  <Direction val="C"/>
                </Update>
              </LogicLine>
              <LogicLine>
                <Update FlowIsn="73">
                  <FieldID val="5"/>
                  <WithValue val="4"/>
                  <Incremental val="N"/>
                  <ForcedUpdate val="Y"/>
                  <Condition val="Y"/>
                  <Modifier val="B"/>
                  <Direction val="C"/>
                </Update>
              </LogicLine>
              <LogicLine>
                <Update FlowIsn="74">
                  <FieldID val="32"/>
                  <WithValue val="20"/>
                  <Incremental val="N"/>
                  <ForcedUpdate val="Y"/>
                  <Condition val="Y"/>
                  <Modifier val="B"/>
                  <Direction val="C"/>
                </Update>
              </LogicLine>
            </LogicLines>
          </LogicUnit>
          <LogicUnit id="4" propagate="78">
            <Level val="T"/>
            <Type val="S"/>
            <Scope val="S"/>
            <EngineDirective val="S"/>
            <ShowMessage val="Y"/>
            <Condition val="89"/>
            <Event>
              <EventType val="S"/>
              <PublicObject comp="-1"/>
            </Event>
            <Expanded val="1"/>
            <LogicLines>
              <LogicLine>
                <Remark FlowIsn="75">
                  <Type val="2"/>
                  <Text val="//28-05-2003 JP SCR #3601 submitter note: check if po.amount is negative"/>
                </Remark>
              </LogicLine>
              <LogicLine>
                <Update FlowIsn="76">
                  <FieldID val="4"/>
                  <WithValue val="1"/>
                  <Incremental val="N"/>
                  <ForcedUpdate val="Y"/>
                  <Condition Exp="15"/>
                  <Modifier val="B"/>
                  <Direction val="C"/>
                </Update>
              </LogicLine>
            </LogicLines>
          </LogicUnit>
          <LogicUnit id="5" propagate="78">
            <Level val="R"/>
            <Type val="S"/>
            <Scope val="S"/>
            <EngineDirective val="S"/>
            <ShowMessage val="Y"/>
            <Condition val="89"/>
            <Event>
              <EventType val="S"/>
              <PublicObject comp="-1"/>
            </Event>
            <Expanded val="1"/>
            <LogicLines>
              <LogicLine>
                <Remark FlowIsn="77">
                  <Type val="2"/>
                  <Text val="check, if limit not possible ( no commercial owner for this debtor !)"/>
                </Remark>
              </LogicLine>
              <LogicLine>
                <Update FlowIsn="78">
                  <FieldID val="32"/>
                  <WithValue val="19"/>
                  <Incremental val="N"/>
                  <ForcedUpdate val="Y"/>
                  <Condition Exp="16"/>
                  <Modifier val="B"/>
                  <Direction val="C"/>
                </Update>
              </LogicLine>
              <LogicLine>
                <Update FlowIsn="79">
                  <FieldID val="6"/>
                  <WithValue val="13"/>
                  <Incremental val="N"/>
                  <ForcedUpdate val="Y"/>
                  <Condition Exp="14"/>
                  <Modifier val="B"/>
                  <Direction val="C"/>
                </Update>
              </LogicLine>
              <LogicLine>
                <Remark FlowIsn="80">
                  <Type val="2"/>
                  <Text val=" "/>
                </Remark>
              </LogicLine>
              <LogicLine>
                <BLOCK EndBlock="84" EndBlockSegment="84" FlowIsn="81" Type="I">
                  <Condition Exp="21"/>
                  <Modifier val="B"/>
                  <Direction val="C"/>
                </BLOCK>
              </LogicLine>
              <LogicLine>
                <Update FlowIsn="82">
                  <FieldID val="32"/>
                  <WithValue val="19"/>
                  <Incremental val="N"/>
                  <ForcedUpdate val="Y"/>
                  <Condition val="Y"/>
                  <Modifier val="B"/>
                  <Direction val="C"/>
                </Update>
              </LogicLine>
              <LogicLine>
                <Update FlowIsn="83">
                  <FieldID val="6"/>
                  <WithValue val="12"/>
                  <Incremental val="N"/>
                  <ForcedUpdate val="Y"/>
                  <Condition val="Y"/>
                  <Modifier val="B"/>
                  <Direction val="C"/>
                </Update>
              </LogicLine>
              <LogicLine>
                <END_BLK FlowIsn="84"/>
              </LogicLine>
              <LogicLine>
                <Remark FlowIsn="85">
                  <Type val="2"/>
                  <Text val=" "/>
                </Remark>
              </LogicLine>
              <LogicLine>
                <Remark FlowIsn="86">
                  <Type val="2"/>
                  <Text val="calculate limit amounts"/>
                </Remark>
              </LogicLine>
              <LogicLine>
                <CallTask FlowIsn="87">
                  <OperationType val="P"/>
                  <TaskID comp="-1" obj="920"/>
                  <Lock val="Y"/>
                  <Arguments>
                    <Argument>
                      <Variable val="31"/>
                      <Skip val="N"/>
                    </Argument>
                    <Argument>
                      <Expression val="10"/>
                      <Skip val="N"/>
                    </Argument>
                    <Argument>
                      <Skip val="Y"/>
                    </Argument>
                    <Argument>
                      <Expression val="17"/>
                      <Skip val="N"/>
                    </Argument>
                    <Argument>
                      <Expression val="9"/>
                      <Skip val="N"/>
                    </Argument>
                    <Argument>
                      <Expression val="8"/>
                      <Skip val="N"/>
                    </Argument>
                    <Argument>
                      <Expression val="11"/>
                      <Skip val="N"/>
                    </Argument>
                    <Argument>
                      <Variable val="33"/>
                      <Skip val="N"/>
                    </Argument>
                    <Argument>
                      <Skip val="Y"/>
                    </Argument>
                  </Arguments>
                  <Wait val="Y"/>
                  <SyncData val="N"/>
                  <RetainFocus val="N"/>
                  <Condition val="Y"/>
                  <Modifier val="B"/>
                  <Direction val="C"/>
                </CallTask>
              </LogicLine>
              <LogicLine>
                <CallTask FlowIsn="88">
                  <OperationType val="P"/>
                  <TaskID comp="-1" obj="920"/>
                  <Lock val="Y"/>
                  <Arguments>
                    <Argument>
                      <Variable val="31"/>
                      <Skip val="N"/>
                    </Argument>
                    <Argument>
                      <Expression val="10"/>
                      <Skip val="N"/>
                    </Argument>
                    <Argument>
                      <Skip val="Y"/>
                    </Argument>
                    <Argument>
                      <Expression val="17"/>
                      <Skip val="N"/>
                    </Argument>
                    <Argument>
                      <Expression val="4"/>
                      <Skip val="N"/>
                    </Argument>
                    <Argument>
                      <Expression val="3"/>
                      <Skip val="N"/>
                    </Argument>
                    <Argument>
                      <Expression val="11"/>
                      <Skip val="N"/>
                    </Argument>
                    <Argument>
                      <Variable val="34"/>
                      <Skip val="N"/>
                    </Argument>
                    <Argument>
                      <Skip val="Y"/>
                    </Argument>
                  </Arguments>
                  <Wait val="Y"/>
                  <SyncData val="N"/>
                  <RetainFocus val="N"/>
                  <Condition val="Y"/>
                  <Modifier val="B"/>
                  <Direction val="C"/>
                </CallTask>
              </LogicLine>
              <LogicLine>
                <Remark FlowIsn="89">
                  <Type val="2"/>
                  <Text val=" "/>
                </Remark>
              </LogicLine>
              <LogicLine>
                <BLOCK EndBlock="93" EndBlockSegment="93" FlowIsn="90" Type="I">
                  <Condition Exp="18"/>
                  <Modifier val="B"/>
                  <Direction val="C"/>
                </BLOCK>
              </LogicLine>
              <LogicLine>
                <Update FlowIsn="91">
                  <FieldID val="4"/>
                  <WithValue val="3"/>
                  <Incremental val="N"/>
                  <ForcedUpdate val="Y"/>
                  <Condition val="Y"/>
                  <Modifier val="B"/>
                  <Direction val="C"/>
                </Update>
              </LogicLine>
              <LogicLine>
                <Update FlowIsn="92">
                  <FieldID val="5"/>
                  <WithValue val="4"/>
                  <Incremental val="N"/>
                  <ForcedUpdate val="Y"/>
                  <Condition val="Y"/>
                  <Modifier val="B"/>
                  <Direction val="C"/>
                </Update>
              </LogicLine>
              <LogicLine>
                <END_BLK FlowIsn="93"/>
              </LogicLine>
              <LogicLine>
                <Remark FlowIsn="94">
                  <Type val="2"/>
                  <Text val=" "/>
                </Remark>
              </LogicLine>
              <LogicLine>
                <Update FlowIsn="95">
                  <FieldID val="7"/>
                  <WithValue val="24"/>
                  <Incremental val="N"/>
                  <ForcedUpdate val="Y"/>
                  <Condition val="Y"/>
                  <Modifier val="B"/>
                  <Direction val="C"/>
                </Update>
              </LogicLine>
            </LogicLines>
          </LogicUnit>
        </TaskLogic>
        <TaskForms>
          <FormEntry id="2">
            <PropertyList model="FORM_GUI0">
              <Font id="50" val="111"/>
              <Color id="51" val="111"/>
              <_Comment id="218"/>
              <FormName id="311" valUnicode="BDC120FL=CheckFL_LimitAllowed"/>
              <_TabbingOrder id="318" val="1"/>
              <WindowType id="358" val="1"/>
              <PersistentFormState id="493"/>
            </PropertyList>
          </FormEntry>
        </TaskForms>
        <Expressions>
          <Expression id="1">
            <ExpSyntax val="0"/>
            <ExpAttribute val="N"/>
          </Expression>
          <Expression id="2">
            <ExpSyntax val="{0,1}"/>
            <ExpAttribute val="N"/>
          </Expression>
          <Expression id="3">
            <ExpSyntax val="{0,2}"/>
            <ExpAttribute val="N"/>
          </Expression>
          <Expression id="4">
            <ExpSyntax val="{0,3}"/>
            <ExpAttribute val="U"/>
          </Expression>
          <Expression id="5">
            <ExpSyntax val="{0,9}"/>
            <ExpAttribute val="N"/>
          </Expression>
          <Expression id="6">
            <ExpSyntax val="{0,10}"/>
            <ExpAttribute val="N"/>
          </Expression>
          <Expression id="7">
            <ExpSyntax val="{0,11}"/>
            <ExpAttribute val="N"/>
          </Expression>
          <Expression id="8">
            <ExpSyntax val="{0,12}"/>
            <ExpAttribute val="N"/>
          </Expression>
          <Expression id="9">
            <ExpSyntax val="{0,13}"/>
            <ExpAttribute val="U"/>
          </Expression>
          <Expression id="10">
            <ExpSyntax val="'H'"/>
            <ExpAttribute val="A"/>
          </Expression>
          <Expression id="11">
            <ExpSyntax val="{0,30}"/>
            <ExpAttribute val="U"/>
          </Expression>
          <Expression id="12">
            <ExpSyntax val="{0,26}"/>
            <ExpAttribute val="U"/>
          </Expression>
          <Expression id="13">
            <ExpSyntax val="{0,27}"/>
            <ExpAttribute val="U"/>
          </Expression>
          <Expression id="14">
            <ExpSyntax val="{0,32}"/>
            <ExpAttribute val="B"/>
          </Expression>
          <Expression id="15">
            <ExpSyntax val="{0,4}&lt;0"/>
            <ExpAttribute val="B"/>
          </Expression>
          <Expression id="16">
            <ExpSyntax val="{0,24}='Y'"/>
            <ExpAttribute val="B"/>
          </Expression>
          <Expression id="17">
            <ExpSyntax val="Date ()"/>
            <ExpAttribute val="D"/>
          </Expression>
          <Expression id="18">
            <ExpSyntax val="NOT ({0,32})"/>
            <ExpAttribute val="B"/>
          </Expression>
          <Expression id="19">
            <ExpSyntax val="'TRUE'LOG"/>
            <ExpAttribute val="B"/>
          </Expression>
          <Expression id="20">
            <ExpSyntax val="'FALSE'LOG"/>
            <ExpAttribute val="B"/>
          </Expression>
          <Expression id="21">
            <ExpSyntax val="{0,23}=2 AND NOT ({0,32})"/>
            <ExpAttribute val="B"/>
          </Expression>
          <Expression id="22">
            <ExpSyntax val="{0,6}"/>
            <ExpAttribute val="U"/>
          </Expression>
          <Expression id="23">
            <ExpSyntax val="GetLang ()"/>
            <ExpAttribute val="A"/>
          </Expression>
          <Expression id="24">
            <ExpSyntax val="{0,19}"/>
            <ExpAttribute val="U"/>
          </Expression>
        </Expressions>
      </Task>
    </Programs>
  </ProgramsRepository>

</Application>
