<?xml version="1.0" encoding="UTF-8" standalone="no" ?>
<Application>

  <Header>
    <Version val="13030.00"/>
    <WithIsn val="Y"/>
    <_InternalTask val="N"/>
    <IsRoot val="N"/>
    <InIndex val="N"/>
    <UniqueISNConvState val="12"/>
  </Header>

  <ProgramsRepository>
    <Programs>
      <Task MainProgram="N">
        <Header Description="Reports - A letters batch" ISN_2="1" LastIsn="3" id="4092">
          <Public val="PLBRR_001"/>
          <ExecutionRight comp="-1"/>
          <Resident val="N"/>
          <SQL val="N"/>
          <ReturnValue>
            <ReturnValueAttr/>
            <ParametersAttributes/>
          </ReturnValue>
          <SqlWhereExist val="N"/>
          <TaskType val="B"/>
          <External val="N"/>
          <Offline val="N"/>
          <FormType val="N"/>
          <DotNetObjectExists val="N"/>
          <LastModified _date="735003" _time="37734" date="15/05/2013" time="10:28:54"/>
        </Header>
        <ItemIsn val="2"/>
        <Resource>
          <DB id="1">
            <DataObject comp="-1" obj="114"/>
            <Access val="R"/>
            <Share val="W"/>
            <Open val="N"/>
            <Cache val="N"/>
            <IdentifyRowModifications val="84"/>
          </DB>
          <DB id="2">
            <DataObject comp="-1" obj="181"/>
            <Access val="R"/>
            <Share val="W"/>
            <Open val="N"/>
            <Cache val="N"/>
            <IdentifyRowModifications val="84"/>
          </DB>
          <DB id="3">
            <DataObject comp="-1" obj="328"/>
            <Access val="R"/>
            <Share val="W"/>
            <Open val="N"/>
            <Cache val="N"/>
            <IdentifyRowModifications val="84"/>
          </DB>
          <DB id="4">
            <DataObject comp="-1" obj="332"/>
            <Access val="R"/>
            <Share val="W"/>
            <Open val="N"/>
            <Cache val="N"/>
            <IdentifyRowModifications val="84"/>
          </DB>
          <DB id="5">
            <DataObject comp="-1" obj="891"/>
            <Access val="R"/>
            <Share val="W"/>
            <Open val="N"/>
            <Cache val="N"/>
            <IdentifyRowModifications val="84"/>
          </DB>
          <DB id="6">
            <DataObject comp="-1" obj="892"/>
            <Access val="R"/>
            <Share val="W"/>
            <Open val="N"/>
            <Cache val="N"/>
            <IdentifyRowModifications val="84"/>
          </DB>
          <DB id="7">
            <DataObject comp="-1" obj="893"/>
            <Access val="R"/>
            <Share val="W"/>
            <Open val="N"/>
            <Cache val="N"/>
            <IdentifyRowModifications val="84"/>
          </DB>
          <DB id="8">
            <DataObject comp="-1" obj="894"/>
            <Access val="R"/>
            <Share val="W"/>
            <Open val="N"/>
            <Cache val="N"/>
            <IdentifyRowModifications val="84"/>
          </DB>
          <DB id="9">
            <DataObject comp="-1" obj="901"/>
            <Access val="R"/>
            <Share val="W"/>
            <Open val="N"/>
            <Cache val="N"/>
            <IdentifyRowModifications val="84"/>
          </DB>
          <DB id="10">
            <DataObject comp="-1" obj="904"/>
            <Access val="R"/>
            <Share val="W"/>
            <Open val="N"/>
            <Cache val="N"/>
            <IdentifyRowModifications val="84"/>
          </DB>
          <DB id="11">
            <DataObject comp="-1" obj="994"/>
            <Access val="R"/>
            <Share val="W"/>
            <Open val="N"/>
            <Cache val="N"/>
            <IdentifyRowModifications val="84"/>
          </DB>
          <Columns>
            <Column id="1" name="v.AS400[F]_Winn[T]">
              <PropertyList model="FIELD">
                <Model attr_obj="FIELD_LOGICAL" id="1"/>
                <StoredAs id="173"/>
                <_FieldStyle id="276" val="1"/>
              </PropertyList>
            </Column>
            <Column id="2" name="v.file_path_name">
              <PropertyList model="FIELD">
                <Model attr_obj="FIELD_UNICODE" id="1"/>
                <Picture id="157" valUnicode="250"/>
                <StoredAs id="173" val="31"/>
                <Size id="174" val="500"/>
                <_Flip id="194"/>
                <_FieldStyle id="276" val="1"/>
              </PropertyList>
            </Column>
          </Columns>
        </Resource>
        <Information>
          <Key>
            <Mode val="N"/>
          </Key>
          <DB comp="-1"/>
          <Sort>
            <CLS val="A"/>
          </Sort>
          <ForceRecordDelete DEL="N"/>
          <EndTaskCondition val="Y"/>
          <EvaluateEndCondition val="B"/>
          <InitialMode val="M"/>
          <Locate Direction="A"/>
          <Range Direction="A"/>
          <VarRange/>
          <TaskProperties>
            <SelectionTable val="N"/>
            <ConfirmUpdate CNFU="N"/>
            <ConfirmCancel val="N"/>
            <ErrorStrategy val="A"/>
            <LockingStrategy val="I"/>
            <CacheStrategy val="T"/>
            <ForceRecordSuffix val="N"/>
            <TransactionMode val="P"/>
            <TransactionBegin val="T"/>
            <PreloadView val="N"/>
            <AllowEmptyDataview val="N"/>
            <KeepCreatedContext val="N"/>
          </TaskProperties>
          <SIDE_WIN>
            <AllowOptions val="N"/>
            <AllowQuery val="Y"/>
            <AllowModify val="Y"/>
            <AllowCreate val="Y"/>
            <AllowDelete val="Y"/>
            <AllowLocate val="Y"/>
            <AllowRange val="Y"/>
            <AllowIndexChange val="Y"/>
            <AllowSorting val="Y"/>
            <AllowIOFiles val="Y"/>
            <RecordCycle val="Y"/>
            <AllowEvents val="Y"/>
            <AllowIndexOptimization val="Y"/>
            <AllowLocationInQuery val="Y"/>
            <AllowPrintingData val="N"/>
          </SIDE_WIN>
          <WIN>
            <OpenTaskWindow val="N"/>
            <CloseTaskWindow val="Y"/>
            <ForegroundWindow val="Y"/>
            <FlipFld val="N"/>
            <RefreshTaskWindow ReturnValue="N"/>
          </WIN>
          <BOX>
            <Direction val="V"/>
          </BOX>
        </Information>
        <TaskLogic>
          <LogicUnit id="2" propagate="78">
            <Level val="R"/>
            <Type val="M"/>
            <Scope val="S"/>
            <EngineDirective val="S"/>
            <ShowMessage val="Y"/>
            <Condition val="89"/>
            <Event>
              <EventType val="S"/>
              <PublicObject comp="-1"/>
            </Event>
            <Expanded val="1"/>
            <LogicLines>
              <LogicLine>
                <DATAVIEW_SRC FlowIsn="2" Type="M">
                  <Condition val="N"/>
                  <Modifier val="B"/>
                  <Direction val="C"/>
                </DATAVIEW_SRC>
              </LogicLine>
              <LogicLine>
                <Remark FlowIsn="3">
                  <Type val="0"/>
                  <Text val=" "/>
                </Remark>
              </LogicLine>
              <LogicLine>
                <Remark FlowIsn="4">
                  <Type val="0"/>
                  <Text val="20.03.2012 GB SCR17205 Added additiona the range CLNT212_FCI = 0"/>
                </Remark>
              </LogicLine>
              <LogicLine>
                <Remark FlowIsn="5">
                  <Type val="0"/>
                  <Text val="08.07.2010 GB SCR15525 Added the DEBC_MARKCODESPECIALACC/for debtor"/>
                </Remark>
              </LogicLine>
              <LogicLine>
                <Remark FlowIsn="6">
                  <Type val="0"/>
                  <Text val="09.02.2010 GB SCR15228 Extended condition for client : CLNT101_ADMNO &lt;> 2 and"/>
                </Remark>
              </LogicLine>
              <LogicLine>
                <Remark FlowIsn="7">
                  <Type val="0"/>
                  <Text val=" CLNT101_ADMNO &lt;> 11"/>
                </Remark>
              </LogicLine>
              <LogicLine>
                <Remark FlowIsn="8">
                  <Type val="0"/>
                  <Text val="22.04.2009 MKO SCR 14 527 create program"/>
                </Remark>
              </LogicLine>
              <LogicLine>
                <Select FieldID="1" FlowIsn="9" id="1">
                  <Column val="1"/>
                  <Type val="V"/>
                  <IsParameter val="N"/>
                  <DIFF_UPDATE val="T"/>
                  <Condition val="Y"/>
                  <Modifier val="S"/>
                  <Direction val="C"/>
                </Select>
              </LogicLine>
              <LogicLine>
                <Remark FlowIsn="10">
                  <Type val="0"/>
                  <Text val=" "/>
                </Remark>
              </LogicLine>
              <LogicLine>
                <Select FieldID="2" FlowIsn="11" id="2">
                  <Column val="2"/>
                  <Type val="V"/>
                  <IsParameter val="N"/>
                  <DIFF_UPDATE val="T"/>
                  <Condition val="Y"/>
                  <Modifier val="S"/>
                  <Direction val="C"/>
                </Select>
              </LogicLine>
              <LogicLine>
                <DATAVIEW_SRC FlowIsn="12" IDX="1" Type="D">
                  <Condition val="N"/>
                  <Modifier val="B"/>
                  <Direction val="C"/>
                </DATAVIEW_SRC>
              </LogicLine>
              <LogicLine>
                <DATAVIEW_SRC FlowIsn="13" IDX="2" Type="D">
                  <Condition val="N"/>
                  <Modifier val="B"/>
                  <Direction val="C"/>
                </DATAVIEW_SRC>
              </LogicLine>
              <LogicLine>
                <DATAVIEW_SRC FlowIsn="14" IDX="3" Type="D">
                  <Condition val="N"/>
                  <Modifier val="B"/>
                  <Direction val="C"/>
                </DATAVIEW_SRC>
              </LogicLine>
              <LogicLine>
                <DATAVIEW_SRC FlowIsn="15" IDX="4" Type="D">
                  <Condition val="N"/>
                  <Modifier val="B"/>
                  <Direction val="C"/>
                </DATAVIEW_SRC>
              </LogicLine>
              <LogicLine>
                <DATAVIEW_SRC FlowIsn="16" IDX="5" Type="D">
                  <Condition val="N"/>
                  <Modifier val="B"/>
                  <Direction val="C"/>
                </DATAVIEW_SRC>
              </LogicLine>
              <LogicLine>
                <DATAVIEW_SRC FlowIsn="17" IDX="6" Type="D">
                  <Condition val="N"/>
                  <Modifier val="B"/>
                  <Direction val="C"/>
                </DATAVIEW_SRC>
              </LogicLine>
              <LogicLine>
                <DATAVIEW_SRC FlowIsn="18" IDX="7" Type="D">
                  <Condition val="N"/>
                  <Modifier val="B"/>
                  <Direction val="C"/>
                </DATAVIEW_SRC>
              </LogicLine>
              <LogicLine>
                <DATAVIEW_SRC FlowIsn="19" IDX="8" Type="D">
                  <Condition val="N"/>
                  <Modifier val="B"/>
                  <Direction val="C"/>
                </DATAVIEW_SRC>
              </LogicLine>
              <LogicLine>
                <DATAVIEW_SRC FlowIsn="20" IDX="9" Type="D">
                  <Condition val="N"/>
                  <Modifier val="B"/>
                  <Direction val="C"/>
                </DATAVIEW_SRC>
              </LogicLine>
              <LogicLine>
                <DATAVIEW_SRC FlowIsn="21" IDX="10" Type="D">
                  <Condition val="N"/>
                  <Modifier val="B"/>
                  <Direction val="C"/>
                </DATAVIEW_SRC>
              </LogicLine>
              <LogicLine>
                <DATAVIEW_SRC FlowIsn="22" IDX="11" Type="D">
                  <Condition val="N"/>
                  <Modifier val="B"/>
                  <Direction val="C"/>
                </DATAVIEW_SRC>
              </LogicLine>
            </LogicLines>
          </LogicUnit>
          <LogicUnit id="3" propagate="78">
            <Level val="T"/>
            <Type val="P"/>
            <Scope val="S"/>
            <EngineDirective val="S"/>
            <ShowMessage val="Y"/>
            <Condition val="89"/>
            <Event>
              <EventType val="S"/>
              <PublicObject comp="-1"/>
            </Event>
            <Expanded val="1"/>
            <LogicLines>
              <LogicLine>
                <Remark FlowIsn="23">
                  <Type val="2"/>
                  <Text val="15.05.2013 JH SCR18105 Removed external flag"/>
                </Remark>
              </LogicLine>
              <LogicLine>
                <Remark FlowIsn="24">
                  <Type val="2"/>
                  <Text val="04.02.2013 SH SCR17678 I/O properties: Changed CharSet = UTF-8 back to Ansi"/>
                </Remark>
              </LogicLine>
              <LogicLine>
                <Remark FlowIsn="25">
                  <Type val="2"/>
                  <Text val="15.06.2009 MKO SCR14694  Change sort order in RAPA key"/>
                </Remark>
              </LogicLine>
              <LogicLine>
                <Remark FlowIsn="26">
                  <Type val="2"/>
                  <Text val="22.04.2009 MKO SCR 14 527 create program"/>
                </Remark>
              </LogicLine>
            </LogicLines>
          </LogicUnit>
          <LogicUnit id="4" propagate="78">
            <Level val="T"/>
            <Type val="S"/>
            <Scope val="S"/>
            <EngineDirective val="S"/>
            <ShowMessage val="Y"/>
            <Condition val="89"/>
            <Event>
              <EventType val="S"/>
              <PublicObject comp="-1"/>
            </Event>
            <Expanded val="1"/>
            <LogicLines>
              <LogicLine>
                <Update FlowIsn="27">
                  <FieldID val="1"/>
                  <WithValue val="1"/>
                  <Incremental val="N"/>
                  <ForcedUpdate val="Y"/>
                  <Condition val="Y"/>
                  <Modifier val="B"/>
                  <Direction val="C"/>
                </Update>
              </LogicLine>
              <LogicLine>
                <CallTask FlowIsn="28">
                  <OperationType val="T"/>
                  <TaskID comp="-1" obj="2"/>
                  <Lock val="N"/>
                  <Wait val="Y"/>
                  <SyncData val="N"/>
                  <RetainFocus val="N"/>
                  <Condition val="Y"/>
                  <Modifier val="B"/>
                  <Direction val="C"/>
                </CallTask>
              </LogicLine>
            </LogicLines>
          </LogicUnit>
        </TaskLogic>
        <TaskForms>
          <FormEntry _last_isn="5" _last_test_id="98" id="2">
            <PropertyList model="FORM_GUI0">
              <Model comp="-1" id="1" obj="371"/>
              <X id="21"/>
              <Y id="22"/>
              <Width id="23" val="320"/>
              <Height id="24" val="160"/>
              <_Comment id="218"/>
              <FormName id="311" valUnicode="Reports - A letters batch"/>
              <_TabbingOrder id="318" val="1"/>
              <WindowType id="358" val="1"/>
              <PersistentFormState id="493"/>
            </PropertyList>
            <Control _test_id="16" id="1">
              <PropertyList model="CTRL_GUI0_STATIC">
                <Model comp="-1" id="1" obj="381"/>
                <Text id="19" valUnicode="Client"/>
                <X id="21" val="3"/>
                <Y id="22" val="8"/>
                <Width id="23" val="51"/>
                <Height id="24" val="12"/>
                <Font id="50" val="111"/>
                <Style id="63" val="7"/>
                <_Orientation id="143"/>
              </PropertyList>
            </Control>
            <Control _test_id="83" id="2">
              <PropertyList model="CTRL_GUI0_STATIC">
                <Model comp="-1" id="1" obj="381"/>
                <Text id="19" valUnicode="204 Commercial contact"/>
                <X id="21" val="3"/>
                <Y id="22" val="24"/>
                <Width id="23" val="59"/>
                <Height id="24" val="12"/>
                <Font id="50" val="111"/>
                <Style id="63" val="7"/>
                <_Orientation id="143"/>
              </PropertyList>
            </Control>
            <Control _test_id="40" id="3">
              <PropertyList model="CTRL_GUI0_STATIC">
                <Model comp="-1" id="1" obj="381"/>
                <Text id="19" valUnicode="Consultant:"/>
                <X id="21" val="3"/>
                <Y id="22" val="40"/>
                <Width id="23" val="106"/>
                <Height id="24" val="12"/>
                <Font id="50" val="111"/>
                <Style id="63" val="7"/>
                <_Orientation id="143"/>
              </PropertyList>
            </Control>
            <Control _test_id="86" id="4">
              <PropertyList model="CTRL_GUI0_STATIC">
                <Text id="19" valUnicode="Debtors range"/>
                <X id="21" val="10"/>
                <Y id="22" val="56"/>
                <Width id="23" val="300"/>
                <Height id="24" val="72"/>
                <Color id="51" val="7"/>
                <Style id="63" val="5"/>
                <StaticType id="70" val="128"/>
                <_VerticalScroll id="73"/>
                <_Orientation id="143"/>
              </PropertyList>
            </Control>
            <Control PDOD="128" _test_id="69" id="5">
              <PropertyList model="CTRL_GUI0_PUSH_BUTTON">
                <Model comp="-1" id="1" obj="385"/>
                <X id="21" val="240"/>
                <Y id="22" val="144"/>
                <Width id="23" val="68"/>
                <Height id="24" val="14"/>
                <ControlName id="46" val="b.make_raport"/>
                <Format id="82" valUnicode="Exit"/>
                <Attribute id="83" val="85"/>
                <RaiseEvent id="234">
                  <EventType val="I"/>
                  <InternalEventID val="222"/>
                  <PublicObject comp="-1"/>
                </RaiseEvent>
                <TabOrder id="314" val="1"/>
              </PropertyList>
            </Control>
          </FormEntry>
        </TaskForms>
        <Expressions>
          <Expression id="1">
            <ExpSyntax val="NOT (Upper (Translate ('%AS400%'))='Y')"/>
            <ExpAttribute val="B"/>
          </Expression>
        </Expressions>
        <Task MainProgram="N">
          <Header Description="for client" ISN_2="2" LastIsn="3" id="4092">
            <ExecutionRight comp="-1"/>
            <Resident val="N"/>
            <SQL val="N"/>
            <ReturnValue>
              <ReturnValueAttr/>
              <ParametersAttributes/>
            </ReturnValue>
            <SqlWhereExist val="N"/>
            <TaskType val="B"/>
            <External val="N"/>
            <FormType val="N"/>
            <DotNetObjectExists val="N"/>
            <LastModified _date="734582" _time="37089" date="20/03/2012" time="10:18:09"/>
          </Header>
          <MAGIC_SQL val="2"/>
          <ItemIsn val="14"/>
          <Resource>
            <DB id="1">
              <DataObject comp="-1" obj="905"/>
              <Access val="R"/>
              <Share val="W"/>
              <Open val="N"/>
              <Cache val="N"/>
              <IdentifyRowModifications val="84"/>
            </DB>
            <DB id="2">
              <DataObject comp="-1" obj="53"/>
              <Access val="R"/>
              <Share val="W"/>
              <Open val="N"/>
              <Cache val="N"/>
              <IdentifyRowModifications val="84"/>
            </DB>
            <DB id="3">
              <DataObject comp="-1" obj="285"/>
              <Access val="R"/>
              <Share val="W"/>
              <Open val="N"/>
              <Cache val="N"/>
              <IdentifyRowModifications val="84"/>
            </DB>
            <Columns>
              <Column id="1" name="v.head">
                <PropertyList model="FIELD">
                  <Model attr_obj="FIELD_LOGICAL" id="1"/>
                  <StoredAs id="173"/>
                  <_FieldStyle id="276" val="1"/>
                </PropertyList>
              </Column>
            </Columns>
          </Resource>
          <Information>
            <Key>
              <Column val="1"/>
              <Mode val="N"/>
            </Key>
            <DB comp="-1" obj="53"/>
            <Sort>
              <CLS val="A"/>
              <Segment>
                <Field val="6"/>
                <Size val="20"/>
                <Direction val="A"/>
              </Segment>
            </Sort>
            <ForceRecordDelete DEL="N"/>
            <EndTaskCondition val="N"/>
            <EvaluateEndCondition val="A"/>
            <InitialMode val="M"/>
            <Locate Direction="A"/>
            <Range Direction="A"/>
            <VarRange LastIsn="5"/>
            <TaskProperties>
              <SelectionTable val="N"/>
              <ConfirmUpdate CNFU="N"/>
              <ConfirmCancel val="N"/>
              <ErrorStrategy val="A"/>
              <LockingStrategy val="M"/>
              <CacheStrategy val="T"/>
              <ForceRecordSuffix val="N"/>
              <TransactionMode val="P"/>
              <TransactionBegin val="N"/>
              <PreloadView val="N"/>
              <AllowEmptyDataview val="N"/>
              <KeepCreatedContext val="N"/>
            </TaskProperties>
            <SIDE_WIN>
              <AllowOptions val="N"/>
              <AllowQuery val="Y"/>
              <AllowModify val="Y"/>
              <AllowCreate val="Y"/>
              <AllowDelete val="Y"/>
              <AllowLocate val="Y"/>
              <AllowRange val="Y"/>
              <AllowIndexChange val="Y"/>
              <AllowSorting val="Y"/>
              <AllowIOFiles val="Y"/>
              <RecordCycle val="Y"/>
              <AllowEvents val="N"/>
              <AllowIndexOptimization val="Y"/>
              <AllowLocationInQuery val="Y"/>
              <AllowPrintingData val="N"/>
            </SIDE_WIN>
            <WIN>
              <OpenTaskWindow val="Y"/>
              <CloseTaskWindow val="N"/>
              <ForegroundWindow val="Y"/>
              <FlipFld val="N"/>
              <RefreshTaskWindow ReturnValue="N"/>
            </WIN>
            <BOX>
              <Direction val="V"/>
            </BOX>
          </Information>
          <TaskLogic>
            <LogicUnit id="2" propagate="78">
              <Level val="R"/>
              <Type val="M"/>
              <Scope val="S"/>
              <EngineDirective val="S"/>
              <ShowMessage val="Y"/>
              <Condition val="89"/>
              <Event>
                <EventType val="S"/>
                <PublicObject comp="-1"/>
              </Event>
              <Expanded val="1"/>
              <LogicLines>
                <LogicLine>
                  <DATAVIEW_SRC FlowIsn="2" IDX="2" Type="M">
                    <Condition val="N"/>
                    <Modifier val="B"/>
                    <Direction val="C"/>
                  </DATAVIEW_SRC>
                </LogicLine>
                <LogicLine>
                  <Select FieldID="1" FlowIsn="3" id="1">
                    <Column val="1"/>
                    <Type val="R"/>
                    <IsParameter val="N"/>
                    <DIFF_UPDATE val="T"/>
                    <Condition val="Y"/>
                    <Modifier val="S"/>
                    <Direction val="C"/>
                  </Select>
                </LogicLine>
                <LogicLine>
                  <Select FieldID="2" FlowIsn="4" id="2">
                    <Column val="2"/>
                    <Type val="R"/>
                    <IsParameter val="N"/>
                    <_DitIndexForToolkit val="1"/>
                    <DIFF_UPDATE val="T"/>
                    <Condition val="Y"/>
                    <Modifier val="S"/>
                    <Direction val="C"/>
                  </Select>
                </LogicLine>
                <LogicLine>
                  <Select FieldID="3" FlowIsn="5" id="3">
                    <Column val="5"/>
                    <Type val="R"/>
                    <IsParameter val="N"/>
                    <DIFF_UPDATE val="T"/>
                    <Condition val="Y"/>
                    <Modifier val="S"/>
                    <Direction val="C"/>
                  </Select>
                </LogicLine>
                <LogicLine>
                  <Select FieldID="4" FlowIsn="6" id="4">
                    <Column val="6"/>
                    <Type val="R"/>
                    <IsParameter val="N"/>
                    <DIFF_UPDATE val="T"/>
                    <Condition val="Y"/>
                    <Modifier val="S"/>
                    <Direction val="C"/>
                  </Select>
                </LogicLine>
                <LogicLine>
                  <Select FieldID="5" FlowIsn="7" id="5">
                    <Column val="15"/>
                    <Type val="R"/>
                    <IsParameter val="N"/>
                    <DIFF_UPDATE val="T"/>
                    <Condition val="Y"/>
                    <Modifier val="S"/>
                    <Direction val="C"/>
                  </Select>
                </LogicLine>
                <LogicLine>
                  <Remark FlowIsn="8">
                    <Type val="0"/>
                    <Text val="CndRange (M,User (0))"/>
                  </Remark>
                </LogicLine>
                <LogicLine>
                  <Remark FlowIsn="9">
                    <Type val="0"/>
                    <Text val="CndRange (P,User (0))"/>
                  </Remark>
                </LogicLine>
                <LogicLine>
                  <Select FieldID="6" FlowIsn="10" id="6">
                    <Column val="40"/>
                    <Type val="R"/>
                    <IsParameter val="N"/>
                    <Range MAX="13" MIN="13"/>
                    <INT_RCMP_INFO>
                      <v>21</v>
                    </INT_RCMP_INFO>
                    <_DitIndexForToolkit val="2"/>
                    <DIFF_UPDATE val="T"/>
                    <Condition val="Y"/>
                    <Modifier val="S"/>
                    <Direction val="C"/>
                  </Select>
                </LogicLine>
                <LogicLine>
                  <Select FieldID="7" FlowIsn="11" id="7">
                    <Column val="41"/>
                    <Type val="R"/>
                    <IsParameter val="N"/>
                    <Range MAX="18" MIN="18"/>
                    <DIFF_UPDATE val="T"/>
                    <Condition val="Y"/>
                    <Modifier val="S"/>
                    <Direction val="C"/>
                  </Select>
                </LogicLine>
                <LogicLine>
                  <Select FieldID="8" FlowIsn="12" id="8">
                    <Column val="210"/>
                    <Type val="R"/>
                    <IsParameter val="N"/>
                    <DIFF_UPDATE val="T"/>
                    <Condition val="Y"/>
                    <Modifier val="S"/>
                    <Direction val="C"/>
                  </Select>
                </LogicLine>
                <LogicLine>
                  <Select FieldID="9" FlowIsn="13" id="9">
                    <Column val="385"/>
                    <Type val="R"/>
                    <IsParameter val="N"/>
                    <Range MAX="1" MIN="1"/>
                    <DIFF_UPDATE val="T"/>
                    <Condition val="Y"/>
                    <Modifier val="S"/>
                    <Direction val="C"/>
                  </Select>
                </LogicLine>
                <LogicLine>
                  <Remark FlowIsn="14">
                    <Type val="0"/>
                    <Text val=" "/>
                  </Remark>
                </LogicLine>
                <LogicLine>
                  <LNK Direction="A" EVL_CND="T" FlowIsn="15" Key="1" Mode="R" SortType="18" VIEW="10" VIEWS="2">
                    <DB comp="-1" obj="905"/>
                    <Expanded val="1"/>
                    <Condition val="Y"/>
                  </LNK>
                </LogicLine>
                <LogicLine>
                  <Select FieldID="10" FlowIsn="16" id="10">
                    <Column val="1"/>
                    <Type val="R"/>
                    <IsParameter val="N"/>
                    <Locate MAX="19" MIN="19"/>
                    <DIFF_UPDATE val="T"/>
                    <Condition val="Y"/>
                    <Modifier val="S"/>
                    <Direction val="C"/>
                  </Select>
                </LogicLine>
                <LogicLine>
                  <Select FieldID="11" FlowIsn="17" id="11">
                    <Column val="2"/>
                    <Type val="R"/>
                    <IsParameter val="N"/>
                    <DIFF_UPDATE val="T"/>
                    <Condition val="Y"/>
                    <Modifier val="S"/>
                    <Direction val="C"/>
                  </Select>
                </LogicLine>
                <LogicLine>
                  <END_LINK FlowIsn="18"/>
                </LogicLine>
                <LogicLine>
                  <Remark FlowIsn="19">
                    <Type val="0"/>
                    <Text val=" "/>
                  </Remark>
                </LogicLine>
                <LogicLine>
                  <Select FieldID="12" FlowIsn="20" id="12">
                    <Column val="1"/>
                    <Type val="V"/>
                    <IsParameter val="N"/>
                    <DIFF_UPDATE val="T"/>
                    <Condition val="Y"/>
                    <Modifier val="S"/>
                    <Direction val="C"/>
                  </Select>
                </LogicLine>
                <LogicLine>
                  <LNK Direction="A" EVL_CND="R" FlowIsn="21" Key="1" Mode="R" SortType="24" VIEW="13" VIEWS="2">
                    <DB comp="-1" obj="285"/>
                    <Expanded val="1"/>
                    <Condition val="Y"/>
                  </LNK>
                </LogicLine>
                <LogicLine>
                  <Select FieldID="13" FlowIsn="22" id="13">
                    <Column val="1"/>
                    <Type val="R"/>
                    <IsParameter val="N"/>
                    <Locate MAX="12" MIN="12"/>
                    <DIFF_UPDATE val="T"/>
                    <Condition val="Y"/>
                    <Modifier val="S"/>
                    <Direction val="C"/>
                  </Select>
                </LogicLine>
                <LogicLine>
                  <Select FieldID="14" FlowIsn="23" id="14">
                    <Column val="6"/>
                    <Type val="R"/>
                    <IsParameter val="N"/>
                    <DIFF_UPDATE val="T"/>
                    <Condition val="Y"/>
                    <Modifier val="S"/>
                    <Direction val="C"/>
                  </Select>
                </LogicLine>
                <LogicLine>
                  <END_LINK FlowIsn="24"/>
                </LogicLine>
              </LogicLines>
            </LogicUnit>
            <LogicUnit id="3" propagate="78">
              <Level val="T"/>
              <Type val="P"/>
              <Scope val="S"/>
              <EngineDirective val="S"/>
              <ShowMessage val="Y"/>
              <Condition val="89"/>
              <Event>
                <EventType val="S"/>
                <PublicObject comp="-1"/>
              </Event>
              <Expanded val="1"/>
              <LogicLines>
                <LogicLine>
                  <CallTask FlowIsn="25">
                    <OperationType val="P"/>
                    <TaskID comp="-1" obj="4219"/>
                    <Lock val="N"/>
                    <Wait val="Y"/>
                    <SyncData val="N"/>
                    <RetainFocus val="N"/>
                    <Condition Exp="7"/>
                    <Modifier val="B"/>
                    <Direction val="C"/>
                  </CallTask>
                </LogicLine>
              </LogicLines>
            </LogicUnit>
            <LogicUnit id="4" propagate="78">
              <Level val="T"/>
              <Type val="S"/>
              <Scope val="S"/>
              <EngineDirective val="S"/>
              <ShowMessage val="Y"/>
              <Condition val="89"/>
              <Event>
                <EventType val="S"/>
                <PublicObject comp="-1"/>
              </Event>
              <Expanded val="1"/>
              <LogicLines>
                <LogicLine>
                  <CallTask FlowIsn="26">
                    <OperationType val="P"/>
                    <TaskID comp="-1" obj="4220"/>
                    <Lock val="N"/>
                    <Wait val="Y"/>
                    <SyncData val="N"/>
                    <RetainFocus val="N"/>
                    <Condition Exp="7"/>
                    <Modifier val="B"/>
                    <Direction val="C"/>
                  </CallTask>
                </LogicLine>
              </LogicLines>
            </LogicUnit>
            <LogicUnit id="5" propagate="78">
              <Level val="G"/>
              <Type val="P"/>
              <FieldID val="6"/>
              <Scope val="S"/>
              <EngineDirective val="S"/>
              <ShowMessage val="Y"/>
              <Condition val="89"/>
              <Event>
                <EventType val="S"/>
                <PublicObject comp="-1"/>
              </Event>
              <Expanded val="1"/>
              <LogicLines>
                <LogicLine>
                  <Update FlowIsn="27">
                    <FieldID val="12"/>
                    <WithValue val="16"/>
                    <Incremental val="N"/>
                    <ForcedUpdate val="Y"/>
                    <Condition val="Y"/>
                    <Modifier val="B"/>
                    <Direction val="C"/>
                  </Update>
                </LogicLine>
                <LogicLine>
                  <BLOCK EndBlock="34" EndBlockSegment="30" FlowIsn="28" Type="I">
                    <Condition Exp="7"/>
                    <Modifier val="B"/>
                    <Direction val="C"/>
                  </BLOCK>
                </LogicLine>
                <LogicLine>
                  <Update FlowIsn="29">
                    <Parent val="1"/>
                    <FieldID val="2"/>
                    <WithValue val="6"/>
                    <Incremental val="N"/>
                    <ForcedUpdate val="Y"/>
                    <Condition val="Y"/>
                    <Modifier val="B"/>
                    <Direction val="C"/>
                  </Update>
                </LogicLine>
                <LogicLine>
                  <BLOCK EndBlock="34" EndBlockSegment="34" FlowIsn="30" Type="E">
                    <Condition val="Y"/>
                    <Modifier val="B"/>
                    <Direction val="C"/>
                  </BLOCK>
                </LogicLine>
                <LogicLine>
                  <Update FlowIsn="31">
                    <Parent val="1"/>
                    <FieldID val="2"/>
                    <WithValue val="5"/>
                    <Incremental val="N"/>
                    <ForcedUpdate val="Y"/>
                    <Condition val="Y"/>
                    <Modifier val="B"/>
                    <Direction val="C"/>
                  </Update>
                </LogicLine>
                <LogicLine>
                  <Remark FlowIsn="32">
                    <Type val="2"/>
                    <Text val="//delet this"/>
                  </Remark>
                </LogicLine>
                <LogicLine>
                  <Update FlowIsn="33">
                    <Parent val="1"/>
                    <FieldID val="2"/>
                    <WithValue val="3"/>
                    <Incremental val="N"/>
                    <ForcedUpdate val="Y"/>
                    <Condition val="N"/>
                    <Modifier val="B"/>
                    <Direction val="C"/>
                  </Update>
                </LogicLine>
                <LogicLine>
                  <END_BLK FlowIsn="34"/>
                </LogicLine>
                <LogicLine>
                  <STP Buttons="O" DefaultButton="1" ERR_LOG_DEF_CHG="N" FlowIsn="35" IMG_DEF_CHG="N" Image="E" Mode="W" TTL_DEF_CHG="N" TXT="Actual path" TitleTxt="Warning" VR_DISP="S">
                    <AppendToErrorLog val="N"/>
                    <Condition val="Y"/>
                    <Modifier val="B"/>
                    <Direction val="C"/>
                  </STP>
                </LogicLine>
                <LogicLine>
                  <STP Buttons="O" DefaultButton="1" ERR_LOG_DEF_CHG="N" Exp="4" FlowIsn="36" IMG_DEF_CHG="N" Image="E" Mode="W" TTL_DEF_CHG="N" TitleTxt="Warning" VR_DISP="S">
                    <AppendToErrorLog val="N"/>
                    <Condition val="Y"/>
                    <Modifier val="B"/>
                    <Direction val="C"/>
                  </STP>
                </LogicLine>
                <LogicLine>
                  <Evaluate FlowIsn="37">
                    <Expression val="15"/>
                    <Condition val="Y"/>
                    <Modifier val="B"/>
                    <Direction val="C"/>
                  </Evaluate>
                </LogicLine>
              </LogicLines>
            </LogicUnit>
            <LogicUnit id="6" propagate="78">
              <Level val="G"/>
              <Type val="S"/>
              <FieldID val="6"/>
              <Scope val="S"/>
              <EngineDirective val="S"/>
              <ShowMessage val="Y"/>
              <Condition val="89"/>
              <Event>
                <EventType val="S"/>
                <PublicObject comp="-1"/>
              </Event>
              <Expanded val="1"/>
              <LogicLines>
                <LogicLine>
                  <BLOCK EndBlock="45" EndBlockSegment="40" FlowIsn="38" Type="I">
                    <Condition Exp="17"/>
                    <Modifier val="B"/>
                    <Direction val="C"/>
                  </BLOCK>
                </LogicLine>
                <LogicLine>
                  <Invoke FlowIsn="39">
                    <OperationType val="O"/>
                    <Command val="4"/>
                    <Wait val="N"/>
                    <Show val="2"/>
                    <Condition Exp="14"/>
                    <Modifier val="B"/>
                    <Direction val="C"/>
                  </Invoke>
                </LogicLine>
                <LogicLine>
                  <BLOCK EndBlock="45" EndBlockSegment="45" FlowIsn="40" Type="E">
                    <Condition val="Y"/>
                    <Modifier val="B"/>
                    <Direction val="C"/>
                  </BLOCK>
                </LogicLine>
                <LogicLine>
                  <CallTask FlowIsn="41">
                    <OperationType val="P"/>
                    <TaskID comp="-1" obj="1711"/>
                    <Lock val="N"/>
                    <Arguments>
                      <Argument>
                        <Expression val="11"/>
                        <Skip val="N"/>
                      </Argument>
                      <Argument>
                        <Expression val="10"/>
                        <Skip val="N"/>
                      </Argument>
                      <Argument>
                        <Skip val="Y"/>
                      </Argument>
                      <Argument>
                        <Skip val="Y"/>
                      </Argument>
                      <Argument>
                        <Expression val="9"/>
                        <Skip val="N"/>
                      </Argument>
                      <Argument>
                        <Skip val="Y"/>
                      </Argument>
                      <Argument>
                        <Expression val="4"/>
                        <Skip val="N"/>
                      </Argument>
                      <Argument>
                        <Skip val="Y"/>
                      </Argument>
                      <Argument>
                        <Skip val="Y"/>
                      </Argument>
                    </Arguments>
                    <Wait val="Y"/>
                    <SyncData val="N"/>
                    <RetainFocus val="N"/>
                    <Condition Exp="14"/>
                    <Modifier val="B"/>
                    <Direction val="C"/>
                  </CallTask>
                </LogicLine>
                <LogicLine>
                  <STP Buttons="O" DefaultButton="1" ERR_LOG_DEF_CHG="N" Exp="8" FlowIsn="42" IMG_DEF_CHG="N" Image="E" Mode="W" TTL_DEF_CHG="N" TitleTxt="Warning" VR_DISP="S">
                    <AppendToErrorLog val="N"/>
                    <Condition val="Y"/>
                    <Modifier val="B"/>
                    <Direction val="C"/>
                  </STP>
                </LogicLine>
                <LogicLine>
                  <STP Buttons="O" DefaultButton="1" ERR_LOG_DEF_CHG="N" FlowIsn="43" IMG_DEF_CHG="N" Image="E" Mode="W" TTL_DEF_CHG="N" TXT="File path:" TitleTxt="Warning" VR_DISP="S">
                    <AppendToErrorLog val="N"/>
                    <Condition val="Y"/>
                    <Modifier val="B"/>
                    <Direction val="C"/>
                  </STP>
                </LogicLine>
                <LogicLine>
                  <STP Buttons="O" DefaultButton="1" ERR_LOG_DEF_CHG="N" Exp="4" FlowIsn="44" IMG_DEF_CHG="N" Image="E" Mode="W" TTL_DEF_CHG="N" TitleTxt="Warning" VR_DISP="S">
                    <AppendToErrorLog val="N"/>
                    <Condition val="Y"/>
                    <Modifier val="B"/>
                    <Direction val="C"/>
                  </STP>
                </LogicLine>
                <LogicLine>
                  <END_BLK FlowIsn="45"/>
                </LogicLine>
              </LogicLines>
            </LogicUnit>
            <LogicUnit id="7" propagate="78">
              <Level val="R"/>
              <Type val="S"/>
              <Scope val="S"/>
              <EngineDirective val="S"/>
              <ShowMessage val="Y"/>
              <Condition val="89"/>
              <Event>
                <EventType val="S"/>
                <PublicObject comp="-1"/>
              </Event>
              <Expanded val="1"/>
              <LogicLines>
                <LogicLine>
                  <CallTask FlowIsn="46">
                    <OperationType val="T"/>
                    <TaskID comp="-1" obj="3"/>
                    <Lock val="N"/>
                    <Wait val="Y"/>
                    <SyncData val="N"/>
                    <RetainFocus val="N"/>
                    <Condition val="Y"/>
                    <Modifier val="B"/>
                    <Direction val="C"/>
                  </CallTask>
                </LogicLine>
              </LogicLines>
            </LogicUnit>
          </TaskLogic>
          <TaskForms>
            <FormEntry _last_isn="3" _last_test_id="7" id="2">
              <PropertyList model="FORM_GUI0">
                <Model comp="-1" id="1" obj="372"/>
                <_Comment id="218"/>
                <FormName id="311" valUnicode="for period"/>
                <_TabbingOrder id="318" val="1"/>
                <WindowType id="358" val="1"/>
                <PersistentFormState id="493"/>
              </PropertyList>
              <Control PDOD="1" _test_id="2" id="1">
                <PropertyList model="CTRL_GUI0_EDIT">
                  <Model comp="-1" id="1" obj="377"/>
                  <X id="21" val="4"/>
                  <Y id="22" val="4"/>
                  <Width id="23" val="27"/>
                  <Height id="24" val="10"/>
                  <Data FieldID="2" id="43"/>
                  <ControlName id="46" val="CLNT102_CLNTNO"/>
                  <ExpansionWindow id="84"/>
                  <_Orientation id="143"/>
                  <TabOrder id="314" val="1"/>
                  <AllowParking id="315" val="Y"/>
                  <AllowedDirection id="317" val="1"/>
                </PropertyList>
              </Control>
              <Control _test_id="4" id="2">
                <PropertyList model="CTRL_GUI0_EDIT">
                  <Model comp="-1" id="1" obj="377"/>
                  <X id="21" val="36"/>
                  <Y id="22" val="4"/>
                  <Width id="23" val="60"/>
                  <Height id="24" val="10"/>
                  <Data FieldID="6" id="43"/>
                  <ControlName id="46" val="CLNT205_EMP_CONTACT_0001"/>
                  <_Orientation id="143"/>
                  <TabOrder id="314" val="2"/>
                  <AllowParking id="315" val="Y"/>
                  <AllowedDirection id="317" val="1"/>
                </PropertyList>
              </Control>
              <Control _test_id="1" id="3">
                <PropertyList model="CTRL_GUI0_STATIC">
                  <Model comp="-1" id="1" obj="382"/>
                  <Text id="19" valUnicode="Generate .."/>
                  <X id="21" val="175"/>
                  <Y id="22" val="36"/>
                  <Width id="23" val="51"/>
                  <Height id="24" val="8"/>
                  <_Orientation id="143"/>
                  <Line3D id="184"/>
                </PropertyList>
              </Control>
            </FormEntry>
          </TaskForms>
          <Expressions>
            <Expression id="1">
              <ExpSyntax val="0"/>
              <ExpAttribute val="N"/>
            </Expression>
            <Expression id="2">
              <ExpSyntax val="{0,1}&lt;>2 AND {0,1}&lt;>11"/>
              <ExpAttribute val="B"/>
            </Expression>
            <Expression id="3">
              <ExpSyntax val="'/factorlink/TEMP/'&amp;Trim ({0,6})&amp;'_report_llettersA.csv'"/>
              <ExpAttribute val="A"/>
            </Expression>
            <Expression id="4">
              <ExpSyntax val="{1,2}"/>
              <ExpAttribute val="U"/>
            </Expression>
            <Expression id="5">
              <ExpSyntax val="Translate ('%TEMP%')&amp;'/'&amp;Trim ({0,6})&amp;'_report_llettersA.csv'"/>
              <ExpAttribute val="A"/>
            </Expression>
            <Expression id="6">
              <ExpSyntax val="Translate ('%TEMP%')&amp;'\'&amp;Trim ({0,6})&amp;'_report_llettersA.csv'"/>
              <ExpAttribute val="A"/>
            </Expression>
            <Expression id="7">
              <ExpSyntax val="{1,1}"/>
              <ExpAttribute val="B"/>
            </Expression>
            <Expression id="8">
              <ExpSyntax val="'Send email by GM102 to:'&amp;Trim ({0,14})"/>
              <ExpAttribute val="A"/>
            </Expression>
            <Expression id="9">
              <ExpSyntax val="MlsTrans ('Reports - A letters')"/>
              <ExpAttribute val="U"/>
            </Expression>
            <Expression id="10">
              <ExpSyntax val="Trim ({0,14})"/>
              <ExpAttribute val="A"/>
            </Expression>
            <Expression id="11">
              <ExpSyntax val="'factorlink@ingcomfin.pl'"/>
              <ExpAttribute val="A"/>
            </Expression>
            <Expression id="12">
              <ExpSyntax val="{0,6}"/>
              <ExpAttribute val="U"/>
            </Expression>
            <Expression id="13">
              <ExpSyntax val="CndRange ({1,1},User (0))"/>
              <ExpAttribute val="A"/>
            </Expression>
            <Expression id="14">
              <ExpSyntax val="{0,12}"/>
              <ExpAttribute val="B"/>
            </Expression>
            <Expression id="15">
              <ExpSyntax val="FileDelete (Trim ({1,2}))"/>
              <ExpAttribute val="B"/>
            </Expression>
            <Expression id="16">
              <ExpSyntax val="'FALSE'LOG"/>
              <ExpAttribute val="B"/>
            </Expression>
            <Expression id="17">
              <ExpSyntax val="{1,1}"/>
              <ExpAttribute val="B"/>
            </Expression>
            <Expression id="18">
              <ExpSyntax val="'AKT'"/>
              <ExpAttribute val="A"/>
            </Expression>
            <Expression id="19">
              <ExpSyntax val="116"/>
              <ExpAttribute val="N"/>
            </Expression>
          </Expressions>
          <VarRangeInfo Mode="F" VarRangeVeeIsn="6" id="1"/>
          <VarRangeInfo Mode="T" VarRangeVeeIsn="6" id="2"/>
          <VarRangeInfo Mode="F" VarRangeVeeIsn="7" id="3"/>
          <VarRangeInfo Mode="T" VarRangeVeeIsn="7" id="4"/>
          <VarRangeInfo Mode="E" VarRangeVeeIsn="9" id="5"/>
          <Task MainProgram="N">
            <Header Description="for debtor" ISN_2="3" LastIsn="3" id="4092">
              <ExecutionRight comp="-1"/>
              <Resident val="N"/>
              <SQL val="N"/>
              <ReturnValue>
                <ReturnValueAttr/>
                <ParametersAttributes/>
              </ReturnValue>
              <SqlWhereExist val="N"/>
              <TaskType val="B"/>
              <External val="N"/>
              <FormType val="N"/>
              <DotNetObjectExists val="N"/>
              <LastModified _date="734903" _time="52963" date="04/02/2013" time="14:42:43"/>
            </Header>
            <MAGIC_SQL val="3"/>
            <ItemIsn val="31"/>
            <Resource>
              <DB id="1">
                <DataObject comp="-1" obj="11"/>
                <Access val="R"/>
                <Share val="W"/>
                <Open val="N"/>
                <Cache val="N"/>
                <IdentifyRowModifications val="84"/>
              </DB>
              <DB id="2">
                <DataObject comp="-1" obj="150"/>
                <Access val="R"/>
                <Share val="W"/>
                <Open val="N"/>
                <Cache val="N"/>
                <IdentifyRowModifications val="84"/>
              </DB>
              <DB id="3">
                <DataObject comp="-1" obj="182"/>
                <Access val="R"/>
                <Share val="W"/>
                <Open val="N"/>
                <Cache val="N"/>
                <IdentifyRowModifications val="84"/>
              </DB>
              <DB id="4">
                <DataObject comp="-1" obj="185"/>
                <Access val="R"/>
                <Share val="W"/>
                <Open val="N"/>
                <Cache val="N"/>
                <IdentifyRowModifications val="84"/>
              </DB>
              <DB id="5">
                <DataObject comp="-1" obj="206"/>
                <Access val="R"/>
                <Share val="W"/>
                <Open val="N"/>
                <Cache val="N"/>
                <IdentifyRowModifications val="84"/>
              </DB>
              <DB id="6">
                <DataObject comp="-1" obj="375"/>
                <Access val="R"/>
                <Share val="W"/>
                <Open val="N"/>
                <Cache val="N"/>
                <IdentifyRowModifications val="84"/>
              </DB>
              <IO id="1">
                <Description val="file"/>
                <IOExpression val="7"/>
                <OpenPrintDialog val="N"/>
                <PaperSize val="68"/>
                <Format val="L"/>
                <Media val="S"/>
                <Access val="A"/>
                <Copies val="1"/>
                <Orientation val="P"/>
                <PrintPreview val="N"/>
                <PDF val="N"/>
                <PrintingAllowed val="Y"/>
                <ContentCopyingAllowed val="Y"/>
                <ChangesAllowed val="Y"/>
                <PageLayoutAllowed val="Y"/>
                <Vis2LogTranslation val="N"/>
                <FlipLines val="N"/>
              </IO>
              <Columns>
                <Column id="1" name="v.exist_arch">
                  <PropertyList model="FIELD">
                    <Model attr_obj="FIELD_LOGICAL" id="1"/>
                    <StoredAs id="173"/>
                    <_FieldStyle id="276" val="1"/>
                  </PropertyList>
                </Column>
                <Column id="2" name="v.line">
                  <PropertyList model="FIELD">
                    <Model attr_obj="FIELD_UNICODE" id="1"/>
                    <Picture id="157" valUnicode="1000"/>
                    <StoredAs id="173" val="31"/>
                    <Size id="174" val="2000"/>
                    <_Flip id="194"/>
                    <_FieldStyle id="276" val="1"/>
                  </PropertyList>
                </Column>
              </Columns>
            </Resource>
            <Information>
              <Key>
                <Column val="3"/>
                <Mode val="N"/>
              </Key>
              <DB comp="-1" obj="185"/>
              <Sort>
                <CLS val="A"/>
              </Sort>
              <ForceRecordDelete DEL="N"/>
              <EndTaskCondition val="N"/>
              <EvaluateEndCondition val="B"/>
              <InitialMode val="M"/>
              <Locate Direction="A"/>
              <Range Direction="A"/>
              <VarRange/>
              <TaskProperties>
                <SelectionTable val="N"/>
                <ConfirmUpdate CNFU="N"/>
                <ConfirmCancel val="N"/>
                <ErrorStrategy val="A"/>
                <LockingStrategy val="M"/>
                <CacheStrategy val="T"/>
                <ForceRecordSuffix val="N"/>
                <TransactionMode val="P"/>
                <TransactionBegin val="N"/>
                <PreloadView val="N"/>
                <AllowEmptyDataview val="N"/>
                <KeepCreatedContext val="N"/>
              </TaskProperties>
              <SIDE_WIN>
                <AllowOptions val="N"/>
                <AllowQuery val="Y"/>
                <AllowModify val="Y"/>
                <AllowCreate val="Y"/>
                <AllowDelete val="Y"/>
                <AllowLocate val="Y"/>
                <AllowRange val="Y"/>
                <AllowIndexChange val="Y"/>
                <AllowSorting val="Y"/>
                <AllowIOFiles val="Y"/>
                <RecordCycle val="Y"/>
                <AllowEvents val="Y"/>
                <AllowIndexOptimization val="Y"/>
                <AllowLocationInQuery val="Y"/>
                <AllowPrintingData val="N"/>
              </SIDE_WIN>
              <WIN>
                <OpenTaskWindow val="N"/>
                <CloseTaskWindow val="Y"/>
                <ForegroundWindow val="Y"/>
                <FlipFld val="N"/>
                <RefreshTaskWindow ReturnValue="N"/>
              </WIN>
              <BOX>
                <Direction val="V"/>
              </BOX>
            </Information>
            <TaskLogic>
              <LogicUnit id="2" propagate="78">
                <Level val="R"/>
                <Type val="M"/>
                <FieldID val="13"/>
                <Scope val="S"/>
                <EngineDirective val="S"/>
                <ShowMessage val="Y"/>
                <Condition val="89"/>
                <Event>
                  <EventType val="S"/>
                  <PublicObject comp="-1"/>
                </Event>
                <Expanded val="1"/>
                <LogicLines>
                  <LogicLine>
                    <DATAVIEW_SRC FlowIsn="2" IDX="4" Type="M">
                      <Condition val="N"/>
                      <Modifier val="B"/>
                      <Direction val="C"/>
                    </DATAVIEW_SRC>
                  </LogicLine>
                  <LogicLine>
                    <Select FieldID="1" FlowIsn="3" id="1">
                      <Column val="1"/>
                      <Type val="R"/>
                      <IsParameter val="N"/>
                      <INT_RCMP_INFO>
                        <v>9</v>
                      </INT_RCMP_INFO>
                      <DIFF_UPDATE val="T"/>
                      <Condition val="Y"/>
                      <Modifier val="S"/>
                      <Direction val="C"/>
                    </Select>
                  </LogicLine>
                  <LogicLine>
                    <Select FieldID="2" FlowIsn="4" id="2">
                      <Column val="8"/>
                      <Type val="R"/>
                      <IsParameter val="N"/>
                      <DIFF_UPDATE val="T"/>
                      <Condition val="Y"/>
                      <Modifier val="S"/>
                      <Direction val="C"/>
                    </Select>
                  </LogicLine>
                  <LogicLine>
                    <Select FieldID="3" FlowIsn="5" id="3">
                      <Column val="27"/>
                      <Type val="R"/>
                      <IsParameter val="N"/>
                      <DIFF_UPDATE val="T"/>
                      <Condition val="Y"/>
                      <Modifier val="S"/>
                      <Direction val="C"/>
                    </Select>
                  </LogicLine>
                  <LogicLine>
                    <Select FieldID="4" FlowIsn="6" id="4">
                      <Column val="28"/>
                      <Type val="R"/>
                      <IsParameter val="N"/>
                      <DIFF_UPDATE val="T"/>
                      <Condition val="Y"/>
                      <Modifier val="S"/>
                      <Direction val="C"/>
                    </Select>
                  </LogicLine>
                  <LogicLine>
                    <Select FieldID="5" FlowIsn="7" id="5">
                      <Column val="10"/>
                      <Type val="R"/>
                      <IsParameter val="N"/>
                      <DIFF_UPDATE val="T"/>
                      <Condition val="Y"/>
                      <Modifier val="S"/>
                      <Direction val="C"/>
                    </Select>
                  </LogicLine>
                  <LogicLine>
                    <Remark FlowIsn="8">
                      <Type val="0"/>
                      <Text val=" "/>
                    </Remark>
                  </LogicLine>
                  <LogicLine>
                    <LNK Direction="A" EVL_CND="R" FlowIsn="9" Key="1" Mode="R" SortType="13" VIEW="6" VIEWS="3">
                      <DB comp="-1" obj="182"/>
                      <Expanded val="1"/>
                      <Condition val="Y"/>
                    </LNK>
                  </LogicLine>
                  <LogicLine>
                    <Select FieldID="6" FlowIsn="10" id="6">
                      <Column val="1"/>
                      <Type val="R"/>
                      <IsParameter val="N"/>
                      <Locate MAX="4" MIN="4"/>
                      <DIFF_UPDATE val="T"/>
                      <Condition val="Y"/>
                      <Modifier val="S"/>
                      <Direction val="C"/>
                    </Select>
                  </LogicLine>
                  <LogicLine>
                    <Select FieldID="7" FlowIsn="11" id="7">
                      <Column val="2"/>
                      <Type val="R"/>
                      <IsParameter val="N"/>
                      <INT_RCMP_INFO>
                        <v>14</v>
                        <v>19</v>
                        <v>38</v>
                      </INT_RCMP_INFO>
                      <DIFF_UPDATE val="T"/>
                      <Condition val="Y"/>
                      <Modifier val="S"/>
                      <Direction val="C"/>
                    </Select>
                  </LogicLine>
                  <LogicLine>
                    <Select FieldID="8" FlowIsn="12" id="8">
                      <Column val="23"/>
                      <Type val="R"/>
                      <IsParameter val="N"/>
                      <DIFF_UPDATE val="T"/>
                      <Condition val="Y"/>
                      <Modifier val="S"/>
                      <Direction val="C"/>
                    </Select>
                  </LogicLine>
                  <LogicLine>
                    <END_LINK FlowIsn="13"/>
                  </LogicLine>
                  <LogicLine>
                    <LNK Direction="A" EVL_CND="R" FlowIsn="14" Key="1" Mode="R" SortType="17" VIEW="9" VIEWS="2">
                      <DB comp="-1" obj="206"/>
                      <Expanded val="1"/>
                      <Condition val="Y"/>
                    </LNK>
                  </LogicLine>
                  <LogicLine>
                    <Select FieldID="9" FlowIsn="15" id="9">
                      <Column val="1"/>
                      <Type val="R"/>
                      <IsParameter val="N"/>
                      <Locate MAX="11" MIN="11"/>
                      <DIFF_UPDATE val="T"/>
                      <Condition val="Y"/>
                      <Modifier val="S"/>
                      <Direction val="C"/>
                    </Select>
                  </LogicLine>
                  <LogicLine>
                    <Select FieldID="10" FlowIsn="16" id="10">
                      <Column val="2"/>
                      <Type val="R"/>
                      <IsParameter val="N"/>
                      <DIFF_UPDATE val="T"/>
                      <Condition val="Y"/>
                      <Modifier val="S"/>
                      <Direction val="C"/>
                    </Select>
                  </LogicLine>
                  <LogicLine>
                    <END_LINK FlowIsn="17"/>
                  </LogicLine>
                  <LogicLine>
                    <Remark FlowIsn="18">
                      <Type val="0"/>
                      <Text val=" "/>
                    </Remark>
                  </LogicLine>
                  <LogicLine>
                    <LNK Direction="D" EVL_CND="R" FieldID="18" FlowIsn="19" Key="1" Mode="R" SortType="27" VIEW="11" VIEWS="7">
                      <DB comp="-1" obj="11"/>
                      <Expanded val="1"/>
                      <Condition val="Y"/>
                    </LNK>
                  </LogicLine>
                  <LogicLine>
                    <Select FieldID="11" FlowIsn="20" id="11">
                      <Column val="1"/>
                      <Type val="R"/>
                      <IsParameter val="N"/>
                      <DIFF_UPDATE val="T"/>
                      <Condition val="Y"/>
                      <Modifier val="S"/>
                      <Direction val="C"/>
                    </Select>
                  </LogicLine>
                  <LogicLine>
                    <Select FieldID="12" FlowIsn="21" id="12">
                      <Column val="2"/>
                      <Type val="R"/>
                      <IsParameter val="N"/>
                      <DIFF_UPDATE val="T"/>
                      <Condition val="Y"/>
                      <Modifier val="S"/>
                      <Direction val="C"/>
                    </Select>
                  </LogicLine>
                  <LogicLine>
                    <Select FieldID="13" FlowIsn="22" id="13">
                      <Column val="3"/>
                      <Type val="R"/>
                      <IsParameter val="N"/>
                      <Locate MAX="22" MIN="22"/>
                      <DIFF_UPDATE val="T"/>
                      <Condition val="Y"/>
                      <Modifier val="S"/>
                      <Direction val="C"/>
                    </Select>
                  </LogicLine>
                  <LogicLine>
                    <Select FieldID="14" FlowIsn="23" id="14">
                      <Column val="4"/>
                      <Type val="R"/>
                      <IsParameter val="N"/>
                      <Locate MAX="23" MIN="23"/>
                      <DIFF_UPDATE val="T"/>
                      <Condition val="Y"/>
                      <Modifier val="S"/>
                      <Direction val="C"/>
                    </Select>
                  </LogicLine>
                  <LogicLine>
                    <Select FieldID="15" FlowIsn="24" id="15">
                      <Column val="5"/>
                      <Type val="R"/>
                      <IsParameter val="N"/>
                      <Locate MAX="21" MIN="21"/>
                      <DIFF_UPDATE val="T"/>
                      <Condition val="Y"/>
                      <Modifier val="S"/>
                      <Direction val="C"/>
                    </Select>
                  </LogicLine>
                  <LogicLine>
                    <Select FieldID="16" FlowIsn="25" id="16">
                      <Column val="8"/>
                      <Type val="R"/>
                      <IsParameter val="N"/>
                      <Locate MAX="20" MIN="19"/>
                      <INT_RCMP_INFO>
                        <v>30</v>
                      </INT_RCMP_INFO>
                      <DIFF_UPDATE val="T"/>
                      <Condition val="Y"/>
                      <Modifier val="S"/>
                      <Direction val="C"/>
                    </Select>
                  </LogicLine>
                  <LogicLine>
                    <Select FieldID="17" FlowIsn="26" id="17">
                      <Column val="6"/>
                      <Type val="R"/>
                      <IsParameter val="N"/>
                      <DIFF_UPDATE val="T"/>
                      <Condition val="Y"/>
                      <Modifier val="S"/>
                      <Direction val="C"/>
                    </Select>
                  </LogicLine>
                  <LogicLine>
                    <END_LINK FlowIsn="27"/>
                  </LogicLine>
                  <LogicLine>
                    <Select FieldID="18" FlowIsn="28" id="18">
                      <Column val="1"/>
                      <Type val="V"/>
                      <IsParameter val="N"/>
                      <DIFF_UPDATE val="T"/>
                      <Condition val="Y"/>
                      <Modifier val="S"/>
                      <Direction val="C"/>
                    </Select>
                  </LogicLine>
                  <LogicLine>
                    <Remark FlowIsn="29">
                      <Type val="0"/>
                      <Text val=" "/>
                    </Remark>
                  </LogicLine>
                  <LogicLine>
                    <LNK Direction="A" EVL_CND="R" FlowIsn="30" Key="3" Mode="R" SortType="36" VIEW="19" VIEWS="5">
                      <DB comp="-1" obj="150"/>
                      <Expanded val="1"/>
                      <Condition val="Y"/>
                    </LNK>
                  </LogicLine>
                  <LogicLine>
                    <Select FieldID="19" FlowIsn="31" id="19">
                      <Column val="1"/>
                      <Type val="R"/>
                      <IsParameter val="N"/>
                      <Locate MAX="18" MIN="18"/>
                      <DIFF_UPDATE val="T"/>
                      <Condition val="Y"/>
                      <Modifier val="S"/>
                      <Direction val="C"/>
                    </Select>
                  </LogicLine>
                  <LogicLine>
                    <Select FieldID="20" FlowIsn="32" id="20">
                      <Column val="4"/>
                      <Type val="R"/>
                      <IsParameter val="N"/>
                      <Locate MAX="17" MIN="17"/>
                      <DIFF_UPDATE val="T"/>
                      <Condition val="Y"/>
                      <Modifier val="S"/>
                      <Direction val="C"/>
                    </Select>
                  </LogicLine>
                  <LogicLine>
                    <Select FieldID="21" FlowIsn="33" id="21">
                      <Column val="3"/>
                      <Type val="R"/>
                      <IsParameter val="N"/>
                      <Locate MAX="16" MIN="16"/>
                      <DIFF_UPDATE val="T"/>
                      <Condition val="Y"/>
                      <Modifier val="S"/>
                      <Direction val="C"/>
                    </Select>
                  </LogicLine>
                  <LogicLine>
                    <Select FieldID="22" FlowIsn="34" id="22">
                      <Column val="2"/>
                      <Type val="R"/>
                      <IsParameter val="N"/>
                      <DIFF_UPDATE val="T"/>
                      <Condition val="Y"/>
                      <Modifier val="S"/>
                      <Direction val="C"/>
                    </Select>
                  </LogicLine>
                  <LogicLine>
                    <Select FieldID="23" FlowIsn="35" id="23">
                      <Column val="5"/>
                      <Type val="R"/>
                      <IsParameter val="N"/>
                      <DIFF_UPDATE val="T"/>
                      <Condition val="Y"/>
                      <Modifier val="S"/>
                      <Direction val="C"/>
                    </Select>
                  </LogicLine>
                  <LogicLine>
                    <END_LINK FlowIsn="36"/>
                  </LogicLine>
                  <LogicLine>
                    <Remark FlowIsn="37">
                      <Type val="0"/>
                      <Text val=" "/>
                    </Remark>
                  </LogicLine>
                  <LogicLine>
                    <LNK Direction="A" EVL_CND="R" FlowIsn="38" Key="16" Mode="R" SortType="46" VIEW="24" VIEWS="7">
                      <DB comp="-1" obj="375"/>
                      <Expanded val="1"/>
                      <Condition val="Y"/>
                    </LNK>
                  </LogicLine>
                  <LogicLine>
                    <Select FieldID="24" FlowIsn="39" id="24">
                      <Column val="1"/>
                      <Type val="R"/>
                      <IsParameter val="N"/>
                      <DIFF_UPDATE val="T"/>
                      <Condition val="Y"/>
                      <Modifier val="S"/>
                      <Direction val="C"/>
                    </Select>
                  </LogicLine>
                  <LogicLine>
                    <Select FieldID="25" FlowIsn="40" id="25">
                      <Column val="2"/>
                      <Type val="R"/>
                      <IsParameter val="N"/>
                      <Locate MAX="10" MIN="10"/>
                      <DIFF_UPDATE val="T"/>
                      <Condition val="Y"/>
                      <Modifier val="S"/>
                      <Direction val="C"/>
                    </Select>
                  </LogicLine>
                  <LogicLine>
                    <Select FieldID="26" FlowIsn="41" id="26">
                      <Column val="5"/>
                      <Type val="R"/>
                      <IsParameter val="N"/>
                      <Locate MAX="9" MIN="9"/>
                      <DIFF_UPDATE val="T"/>
                      <Condition val="Y"/>
                      <Modifier val="S"/>
                      <Direction val="C"/>
                    </Select>
                  </LogicLine>
                  <LogicLine>
                    <Select FieldID="27" FlowIsn="42" id="27">
                      <Column val="7"/>
                      <Type val="R"/>
                      <IsParameter val="N"/>
                      <DIFF_UPDATE val="T"/>
                      <Condition val="Y"/>
                      <Modifier val="S"/>
                      <Direction val="C"/>
                    </Select>
                  </LogicLine>
                  <LogicLine>
                    <Select FieldID="28" FlowIsn="43" id="28">
                      <Column val="3"/>
                      <Type val="R"/>
                      <IsParameter val="N"/>
                      <Locate MAX="22" MIN="22"/>
                      <DIFF_UPDATE val="T"/>
                      <Condition val="Y"/>
                      <Modifier val="S"/>
                      <Direction val="C"/>
                    </Select>
                  </LogicLine>
                  <LogicLine>
                    <Select FieldID="29" FlowIsn="44" id="29">
                      <Column val="4"/>
                      <Type val="R"/>
                      <IsParameter val="N"/>
                      <Locate MAX="23" MIN="23"/>
                      <DIFF_UPDATE val="T"/>
                      <Condition val="Y"/>
                      <Modifier val="S"/>
                      <Direction val="C"/>
                    </Select>
                  </LogicLine>
                  <LogicLine>
                    <Select FieldID="30" FlowIsn="45" id="30">
                      <Column val="9"/>
                      <Type val="R"/>
                      <IsParameter val="N"/>
                      <Locate MAX="8" MIN="8"/>
                      <DIFF_UPDATE val="T"/>
                      <Condition val="Y"/>
                      <Modifier val="S"/>
                      <Direction val="C"/>
                    </Select>
                  </LogicLine>
                  <LogicLine>
                    <END_LINK FlowIsn="46"/>
                  </LogicLine>
                  <LogicLine>
                    <Remark FlowIsn="47">
                      <Type val="0"/>
                      <Text val=" "/>
                    </Remark>
                  </LogicLine>
                  <LogicLine>
                    <Select FieldID="31" FlowIsn="48" id="31">
                      <Column val="2"/>
                      <Type val="V"/>
                      <IsParameter val="N"/>
                      <DIFF_UPDATE val="T"/>
                      <Condition val="Y"/>
                      <Modifier val="S"/>
                      <Direction val="C"/>
                    </Select>
                  </LogicLine>
                </LogicLines>
              </LogicUnit>
              <LogicUnit id="3" propagate="78">
                <Level val="R"/>
                <Type val="S"/>
                <FieldID val="13"/>
                <Scope val="S"/>
                <EngineDirective val="S"/>
                <ShowMessage val="Y"/>
                <Condition val="89"/>
                <Event>
                  <EventType val="S"/>
                  <PublicObject comp="-1"/>
                </Event>
                <Expanded val="1"/>
                <LogicLines>
                  <LogicLine>
                    <BLOCK EndBlock="61" EndBlockSegment="61" FlowIsn="49" Type="I">
                      <Condition Exp="1"/>
                      <Modifier val="B"/>
                      <Direction val="C"/>
                    </BLOCK>
                  </LogicLine>
                  <LogicLine>
                    <BLOCK EndBlock="54" EndBlockSegment="54" FlowIsn="50" Type="I">
                      <Condition Exp="6"/>
                      <Modifier val="B"/>
                      <Direction val="C"/>
                    </BLOCK>
                  </LogicLine>
                  <LogicLine>
                    <Update FlowIsn="51">
                      <Parent val="2"/>
                      <FieldID val="12"/>
                      <WithValue val="2"/>
                      <Incremental val="N"/>
                      <ForcedUpdate val="Y"/>
                      <Condition val="Y"/>
                      <Modifier val="B"/>
                      <Direction val="C"/>
                    </Update>
                  </LogicLine>
                  <LogicLine>
                    <Update FlowIsn="52">
                      <FieldID val="31"/>
                      <WithValue val="5"/>
                      <Incremental val="N"/>
                      <ForcedUpdate val="Y"/>
                      <Condition val="Y"/>
                      <Modifier val="B"/>
                      <Direction val="C"/>
                    </Update>
                  </LogicLine>
                  <LogicLine>
                    <FormIO FlowIsn="53">
                      <OperationType val="O"/>
                      <Page val="A"/>
                      <IODeviceInfo>
                        <IoDeviceIndex val="1"/>
                      </IODeviceInfo>
                      <FormEntryInfo>
                        <FormEntryIndex val="3"/>
                      </FormEntryInfo>
                      <Condition val="Y"/>
                      <Modifier val="B"/>
                      <Direction val="C"/>
                    </FormIO>
                  </LogicLine>
                  <LogicLine>
                    <END_BLK FlowIsn="54"/>
                  </LogicLine>
                  <LogicLine>
                    <Remark FlowIsn="55">
                      <Type val="2"/>
                      <Text val=" "/>
                    </Remark>
                  </LogicLine>
                  <LogicLine>
                    <Update FlowIsn="56">
                      <FieldID val="31"/>
                      <WithValue val="12"/>
                      <Incremental val="N"/>
                      <ForcedUpdate val="Y"/>
                      <Condition val="Y"/>
                      <Modifier val="B"/>
                      <Direction val="C"/>
                    </Update>
                  </LogicLine>
                  <LogicLine>
                    <Update FlowIsn="57">
                      <FieldID val="31"/>
                      <WithValue val="14"/>
                      <Incremental val="N"/>
                      <ForcedUpdate val="Y"/>
                      <Condition val="Y"/>
                      <Modifier val="B"/>
                      <Direction val="C"/>
                    </Update>
                  </LogicLine>
                  <LogicLine>
                    <Update FlowIsn="58">
                      <FieldID val="31"/>
                      <WithValue val="15"/>
                      <Incremental val="N"/>
                      <ForcedUpdate val="Y"/>
                      <Condition val="Y"/>
                      <Modifier val="B"/>
                      <Direction val="C"/>
                    </Update>
                  </LogicLine>
                  <LogicLine>
                    <Update FlowIsn="59">
                      <FieldID val="31"/>
                      <WithValue val="13"/>
                      <Incremental val="N"/>
                      <ForcedUpdate val="Y"/>
                      <Condition val="Y"/>
                      <Modifier val="B"/>
                      <Direction val="C"/>
                    </Update>
                  </LogicLine>
                  <LogicLine>
                    <FormIO FlowIsn="60">
                      <OperationType val="O"/>
                      <Page val="A"/>
                      <IODeviceInfo>
                        <IoDeviceIndex val="1"/>
                      </IODeviceInfo>
                      <FormEntryInfo>
                        <FormEntryIndex val="3"/>
                      </FormEntryInfo>
                      <Condition val="Y"/>
                      <Modifier val="B"/>
                      <Direction val="C"/>
                    </FormIO>
                  </LogicLine>
                  <LogicLine>
                    <END_BLK FlowIsn="61"/>
                  </LogicLine>
                </LogicLines>
              </LogicUnit>
            </TaskLogic>
            <TaskForms>
              <FormEntry _last_test_id="124" id="2">
                <PropertyList model="FORM_GUI0">
                  <Width id="23" val="714"/>
                  <Height id="24" val="288"/>
                  <_Comment id="218"/>
                  <FormName id="311" valUnicode="for debtor"/>
                  <_TabbingOrder id="318" val="1"/>
                  <WindowType id="358" val="1"/>
                  <PersistentFormState id="493"/>
                </PropertyList>
              </FormEntry>
            </TaskForms>
            <TaskForms>
              <FormEntry CLSS="1" _last_isn="1" _last_test_id="3" id="3">
                <PropertyList model="FORM_TEXT">
                  <Width id="23" val="1000"/>
                  <Height id="24" val="1"/>
                  <_Comment id="218"/>
                  <FormName id="311" valUnicode="line"/>
                </PropertyList>
                <Control _test_id="1" id="1">
                  <PropertyList model="CTRL_TEXT_EDIT">
                    <Model ID="MODEL_TEXTBASE" id="1">
                      <Var FieldID="31"/>
                    </Model>
                    <Width id="23" val="1000"/>
                    <Height id="24" val="1"/>
                    <Data FieldID="31" id="43"/>
                    <_Orientation id="143"/>
                  </PropertyList>
                </Control>
              </FormEntry>
            </TaskForms>
            <Expressions>
              <Expression id="1">
                <ExpSyntax val="NOT ({0,18})"/>
                <ExpAttribute val="B"/>
              </Expression>
              <Expression id="2">
                <ExpSyntax val="'TRUE'LOG"/>
                <ExpAttribute val="B"/>
              </Expression>
              <Expression id="3">
                <ExpSyntax val="{0,3}={2,1} AND {0,4}={2,2} AND {0,2}&lt;>0"/>
                <ExpAttribute val="B"/>
              </Expression>
              <Expression id="4">
                <ExpSyntax val="{0,1}"/>
                <ExpAttribute val="N"/>
              </Expression>
              <Expression id="5">
                <ExpSyntax val="Trim ({2,11})"/>
                <ExpAttribute val="A"/>
              </Expression>
              <Expression id="6">
                <ExpSyntax val="NOT ({2,12})"/>
                <ExpAttribute val="B"/>
              </Expression>
              <Expression id="7">
                <ExpSyntax val="Trim ({1,2})"/>
                <ExpAttribute val="A"/>
              </Expression>
              <Expression id="8">
                <ExpSyntax val="'LTI'"/>
                <ExpAttribute val="A"/>
              </Expression>
              <Expression id="9">
                <ExpSyntax val="{0,7}"/>
                <ExpAttribute val="N"/>
              </Expression>
              <Expression id="10">
                <ExpSyntax val="'MAB'"/>
                <ExpAttribute val="A"/>
              </Expression>
              <Expression id="11">
                <ExpSyntax val="{0,7}"/>
                <ExpAttribute val="N"/>
              </Expression>
              <Expression id="12">
                <ExpSyntax val="''"/>
                <ExpAttribute val="A"/>
              </Expression>
              <Expression id="13">
                <ExpSyntax val="Trim ({0,31})&amp;IF (ISNULL ({0,17}),'-',DStr ({0,17},'YYYY-MM-DD'))&amp;';'&amp;IF (ISNULL ({0,27}),'-',DStr ({0,27},'YYYY-MM-DD'))&amp;';'&amp;Trim (Str ({0,8},'3'))&amp;';'"/>
                <ExpAttribute val="A"/>
              </Expression>
              <Expression id="14">
                <ExpSyntax val="Trim (Str ({0,3},'4'))&amp;';'&amp;Trim (Str ({0,4},'5'))&amp;';'&amp;Trim (Str ({0,7},'9'))&amp;';'&amp;Trim ({2,6})&amp;';'&amp;Trim ({0,10})&amp;';'"/>
                <ExpAttribute val="A"/>
              </Expression>
              <Expression id="15">
                <ExpSyntax val="Trim ({0,31})&amp;Trim (Str ({0,2},'N11.2C'))&amp;';'&amp;Trim (Str ({0,5},'N11.2C'))&amp;';'&amp;Trim ({0,23})&amp;';'"/>
                <ExpAttribute val="A"/>
              </Expression>
              <Expression id="16">
                <ExpSyntax val="{0,16}"/>
                <ExpAttribute val="N"/>
              </Expression>
              <Expression id="17">
                <ExpSyntax val="GetParam ('GNRL_CODE')"/>
                <ExpAttribute val="*"/>
              </Expression>
              <Expression id="18">
                <ExpSyntax val="70"/>
                <ExpAttribute val="N"/>
              </Expression>
              <Expression id="19">
                <ExpSyntax val="30"/>
                <ExpAttribute val="N"/>
              </Expression>
              <Expression id="20">
                <ExpSyntax val="31"/>
                <ExpAttribute val="N"/>
              </Expression>
              <Expression id="21">
                <ExpSyntax val="{0,7}"/>
                <ExpAttribute val="N"/>
              </Expression>
              <Expression id="22">
                <ExpSyntax val="{2,1}"/>
                <ExpAttribute val="N"/>
              </Expression>
              <Expression id="23">
                <ExpSyntax val="{2,2}"/>
                <ExpAttribute val="N"/>
              </Expression>
            </Expressions>
          </Task>
        </Task>
      </Task>
    </Programs>
  </ProgramsRepository>

</Application>
