<?xml version="1.0" encoding="UTF-8" standalone="no" ?>
<Application>

  <Header>
    <Version val="13030.00"/>
    <WithIsn val="Y"/>
    <_InternalTask val="N"/>
    <IsRoot val="N"/>
    <InIndex val="N"/>
    <UniqueISNConvState val="12"/>
  </Header>

  <ProgramsRepository>
    <Programs>
      <Task MainProgram="N">
        <Header Description="BAD011N BAD011 in a new Queue" ISN_2="1" LastIsn="1" id="1572">
          <Public val="BAD011N"/>
          <ExecutionRight comp="-1"/>
          <Resident val="N"/>
          <SQL val="N"/>
          <ReturnValue>
            <ReturnValueAttr/>
            <ParametersAttributes/>
          </ReturnValue>
          <SqlWhereExist val="N"/>
          <TaskType val="B"/>
          <External val="N"/>
          <Offline val="N"/>
          <FormType val="N"/>
          <DotNetObjectExists val="N"/>
          <LastModified _date="734987" _time="59560" date="29/04/2013" time="16:32:40"/>
        </Header>
        <Resource>
          <Columns/>
        </Resource>
        <Information>
          <Key>
            <Mode val="N"/>
          </Key>
          <DB comp="-1"/>
          <Sort>
            <CLS val="A"/>
          </Sort>
          <ForceRecordDelete DEL="N"/>
          <EndTaskCondition val="Y"/>
          <EvaluateEndCondition val="A"/>
          <InitialMode val="E"/>
          <Locate Direction="A"/>
          <Range Direction="A"/>
          <VarRange/>
          <TaskProperties>
            <SelectionTable val="N"/>
            <ConfirmUpdate CNFU="N"/>
            <ConfirmCancel val="N"/>
            <ErrorStrategy val="A"/>
            <LockingStrategy val="I"/>
            <CacheStrategy val="T"/>
            <ForceRecordSuffix val="N"/>
            <TransactionMode val="P"/>
            <TransactionBegin val="T"/>
            <PreloadView val="N"/>
            <AllowEmptyDataview val="N"/>
            <KeepCreatedContext val="N"/>
          </TaskProperties>
          <SIDE_WIN>
            <AllowOptions val="N"/>
            <AllowQuery val="Y"/>
            <AllowModify val="Y"/>
            <AllowCreate val="Y"/>
            <AllowDelete val="Y"/>
            <AllowLocate val="Y"/>
            <AllowRange val="Y"/>
            <AllowIndexChange val="Y"/>
            <AllowSorting val="Y"/>
            <AllowIOFiles val="Y"/>
            <RecordCycle val="Y"/>
            <AllowEvents val="N"/>
            <AllowIndexOptimization val="Y"/>
            <AllowLocationInQuery val="Y"/>
            <AllowPrintingData val="N"/>
          </SIDE_WIN>
          <WIN>
            <OpenTaskWindow val="N"/>
            <CloseTaskWindow val="Y"/>
            <ForegroundWindow val="N"/>
            <FlipFld val="N"/>
            <RefreshTaskWindow ReturnValue="N"/>
          </WIN>
          <BOX>
            <Direction val="V"/>
          </BOX>
        </Information>
        <TaskLogic>
          <LogicUnit id="2" propagate="78">
            <Level val="R"/>
            <Type val="M"/>
            <Scope val="S"/>
            <EngineDirective val="S"/>
            <ShowMessage val="Y"/>
            <Condition val="89"/>
            <Event>
              <EventType val="S"/>
              <PublicObject comp="-1"/>
            </Event>
            <Expanded val="1"/>
            <LogicLines>
              <LogicLine>
                <DATAVIEW_SRC FlowIsn="2" Type="M">
                  <Condition val="N"/>
                  <Modifier val="B"/>
                  <Direction val="C"/>
                </DATAVIEW_SRC>
              </LogicLine>
            </LogicLines>
          </LogicUnit>
          <LogicUnit id="3" propagate="78">
            <Level val="T"/>
            <Type val="P"/>
            <Scope val="S"/>
            <EngineDirective val="S"/>
            <ShowMessage val="Y"/>
            <Condition val="89"/>
            <Event>
              <EventType val="S"/>
              <PublicObject comp="-1"/>
            </Event>
            <Expanded val="1"/>
            <LogicLines>
              <LogicLine>
                <Remark FlowIsn="3">
                  <Type val="2"/>
                  <Text val="this Program starts the Program BAD011 in Queue:"/>
                </Remark>
              </LogicLine>
              <LogicLine>
                <Remark FlowIsn="4">
                  <Type val="2"/>
                  <Text val="     JOBQ MSE/MGSRVN_1UL and release this Jobq"/>
                </Remark>
              </LogicLine>
              <LogicLine>
                <Remark FlowIsn="5">
                  <Type val="2"/>
                  <Text val=" "/>
                </Remark>
              </LogicLine>
              <LogicLine>
                <Remark FlowIsn="6">
                  <Type val="2"/>
                  <Text val="29.04.2013 JH SCR18105 Removed external flag"/>
                </Remark>
              </LogicLine>
              <LogicLine>
                <Remark FlowIsn="7">
                  <Type val="2"/>
                  <Text val="13.04.2010 SH SCR15431 Replaced hardcoded jobqueue names by logical names"/>
                </Remark>
              </LogicLine>
              <LogicLine>
                <Remark FlowIsn="8">
                  <Type val="2"/>
                  <Text val=" "/>
                </Remark>
              </LogicLine>
              <LogicLine>
                <Evaluate FlowIsn="9">
                  <Expression val="1"/>
                  <Condition val="Y"/>
                  <Modifier val="B"/>
                  <Direction val="C"/>
                </Evaluate>
              </LogicLine>
              <LogicLine>
                <CallTask FlowIsn="10">
                  <OperationType val="P"/>
                  <TaskID comp="-1" obj="2449"/>
                  <Lock val="N"/>
                  <Arguments>
                    <Argument>
                      <Expression val="2"/>
                      <Skip val="N"/>
                    </Argument>
                  </Arguments>
                  <Wait val="Y"/>
                  <SyncData val="N"/>
                  <RetainFocus val="N"/>
                  <Condition val="Y"/>
                  <Modifier val="B"/>
                  <Direction val="C"/>
                </CallTask>
              </LogicLine>
              <LogicLine>
                <CallTask FlowIsn="11">
                  <OperationType val="P"/>
                  <TaskID comp="-1" obj="2467"/>
                  <Lock val="N"/>
                  <Arguments>
                    <Argument>
                      <Expression val="3"/>
                      <Skip val="N"/>
                    </Argument>
                  </Arguments>
                  <Wait val="Y"/>
                  <SyncData val="N"/>
                  <RetainFocus val="N"/>
                  <Condition val="Y"/>
                  <Modifier val="B"/>
                  <Direction val="C"/>
                </CallTask>
              </LogicLine>
            </LogicLines>
          </LogicUnit>
        </TaskLogic>
        <TaskForms>
          <FormEntry id="2">
            <PropertyList model="FORM_GUI0">
              <_Comment id="218"/>
              <FormName id="311" valUnicode="BAD011N BAD011 in a new Queue"/>
              <_TabbingOrder id="318" val="1"/>
              <WindowType id="358" val="1"/>
              <PersistentFormState id="493"/>
            </PropertyList>
          </FormEntry>
        </TaskForms>
        <Expressions>
          <Expression id="1">
            <ExpSyntax val="INIPut ('[MAGIC_LOGICAL_NAMES]JOBQ2='&amp;Trim (Translate ('%MAGICLIB%'))&amp;'/'&amp;Trim (Translate ('%JOBQUEUE_ULTIMO_1%')),'FALSE'LOG)"/>
            <ExpAttribute val="B"/>
          </Expression>
          <Expression id="2">
            <ExpSyntax val="'BAD011'"/>
            <ExpAttribute val="A"/>
          </Expression>
          <Expression id="3">
            <ExpSyntax val="'RLSJOBQ '&amp;Trim (Translate ('%MAGICLIB%'))&amp;'/'&amp;Trim (Translate ('%JOBQUEUE_ULTIMO_1%'))"/>
            <ExpAttribute val="A"/>
          </Expression>
        </Expressions>
      </Task>
    </Programs>
  </ProgramsRepository>

</Application>
